main.v
module clock_handler (
    input clk,
    input AM_PM,
    input set_time,
    input [7:0] input_sec,
    input [7:0] input_min,
    input [7:0] input_hour,

    output reg [7:0] current_24_sec,
    output reg [7:0] current_24_min,
    output reg [7:0] current_24_hour,
    output reg [7:0] display_sec,
    output reg [7:0] display_min,
    output reg [7:0] display_hour,
    output reg is_pm
);

// synchronous time set
always @(posedge clk) begin
    if (set_time == 1'd1) begin
        current_24_sec  <= input_sec;
        current_24_min  <= input_min;
        current_24_hour <= input_hour;
    end else begin
        if (current_24_sec == 8'd59) begin
            current_24_sec <= 8'd0;
            if (current_24_min == 8'd59) begin
                current_24_min <= 8'd0;
                if (current_24_hour == 8'd23) begin
                    current_24_hour <= 8'd0;
                end else begin
                    current_24_hour <= current_24_hour + 1;
                end
            end else begin
                current_24_min <= current_24_min + 1;
            end
        end else begin
            current_24_sec <= current_24_sec + 1;
        end
    end
end

// Display time in 12-hour or 24-hour format
always @(*) begin
    display_sec <= current_24_sec;
    display_min <= current_24_min;

    if (AM_PM == 1'b1) begin  // 12-hour format
        if (current_24_hour == 0) begin
            display_hour <= 8'd12;  // 12 AM (midnight)
        end else if (current_24_hour == 12) begin
            display_hour <= 8'd12;  // 12 PM (noon)
        end else if (current_24_hour > 12) begin
            display_hour <= current_24_hour - 12;  // PM hours
        end else begin
            display_hour <= current_24_hour;  // AM hours
        end
    end else begin  // 24-hour format
        display_hour <= current_24_hour;
    end

    if (AM_PM == 1'b1) begin  // 12-hour format
        is_pm <= (current_24_hour >= 12) ? 1'b1 : 1'b0;
    end else begin
        is_pm <= 1'b0;  // Don't care in 24-hour mode
    end
end
endmodule

module date_handler (
    input clk,
    input reset,
    input set_date,
    input [7:0] input_day,
    input [7:0] input_month,
    input [15:0] input_year,

    // Clock time inputs to detect day changes
    input [7:0] current_24_hour,
    input [7:0] current_24_min,
    input [7:0] current_24_sec,

    // Date outputs
    output reg [ 7:0] current_day,
    output reg [ 7:0] current_month,
    output reg [15:0] current_year
);

// Internal signals
reg [7:0] days_in_current_month;

// Date handling logic
always @(posedge clk or posedge reset) begin
    if (reset) begin
        // Reset to default date
        current_day   <= 8'd1;
        current_month <= 8'd1;
        current_year  <= 16'd2020;

    end else if (set_date) begin
        // Set date manually when set_date is active
        current_day   <= input_day;
        current_month <= input_month;
        current_year  <= input_year;

    end else if (current_24_hour == 8'd23 && current_24_min == 8'd59 && current_24_sec == 8'd59) begin
        // Day changes at midnight (23:59:59)

        // First determine days in current month without using a function
        case (current_month)
            8'd1, 8'd3, 8'd5, 8'd7, 8'd8, 8'd10, 8'd12:
                days_in_current_month = 8'd31;  // Jan, Mar, May, Jul, Aug, Oct, Dec

            8'd4, 8'd6, 8'd9, 8'd11: days_in_current_month = 8'd30;  // Apr, Jun, Sep, Nov

            8'd2: begin  // February
                // Check leap year
                if (((current_year % 4 == 0) && (current_year % 100 != 0)) || (current_year % 400 == 0))
                    days_in_current_month = 8'd29;  // Leap year
                else days_in_current_month = 8'd28;  // Non-leap year
            end

            default: days_in_current_month = 8'd30;  // Default case
        endcase

        // Update date
        if (current_day == days_in_current_month) begin
            current_day <= 8'd1;  // Reset day to 1

            if (current_month == 8'd12) begin
                current_month <= 8'd1;  // Reset month to January
                current_year  <= current_year + 16'd1;  // Increment year
            end else begin
                current_month <= current_month + 8'd1;  // Increment month
            end
        end else begin
            current_day <= current_day + 8'd1;  // Increment day
        end
    end
end

endmodule

module alarm_handler (
    input clk,

    input [7:0] input_sec,
    input [7:0] input_min,
    input [7:0] input_hour,

    input [7:0] alarm_time_sec,
    input [7:0] alarm_time_min,
    input [7:0] alarm_time_hour,

    output reg alarm_sound
);

always @(posedge clk) begin
    if (input_sec == alarm_time_sec && input_min == alarm_time_min && input_hour == alarm_time_hour) begin
        alarm_sound <= 1;
    end else begin
        alarm_sound <= 0;
    end
end

endmodule

module timer_handler (
    input clk,
    input reset,
    input start_timer,
    input stop_timer,
    input set_timer,
    input [7:0] input_min,
    input [7:0] input_sec,

    output reg [7:0] timer_min,
    output reg [7:0] timer_sec,
    output reg timer_running,
    output reg timer_done
);


reg [7:0] max_min = 8'd10;

always @(posedge clk or posedge reset) begin
    if (reset) begin
        timer_min <= 8'd0;
        timer_sec <= 8'd0;
        timer_running <= 1'b0;
        timer_done <= 1'b0;
    end else if (set_timer) begin
        if (input_min > max_min) begin
            // Limit to maximum 10 minutes
            timer_min <= max_min;
            timer_sec <= input_sec;
        end else begin
            timer_min <= input_min;
            timer_sec <= input_sec;
        end
        timer_running <= 1'b0;
        timer_done <= 1'b0;
    end else if (start_timer) begin
        timer_running <= 1'b1;
        timer_done <= 1'b0;
    end else if (stop_timer) begin
        // Stop the timer
        timer_running <= 1'b0;
    end

    if (timer_running) begin
        // Timer is running, decrement
        if (timer_sec == 8'd0) begin
            if (timer_min == 8'd0) begin
                // Timer has reached zero
                timer_running <= 1'b0;
                timer_done <= 1'b1;
            end else begin
                // Decrement minute, reset seconds to 59
                timer_min <= timer_min - 8'd1;
                timer_sec <= 8'd59;
            end
        end else begin
            // Decrement seconds
            timer_sec <= timer_sec - 8'd1;
        end
    end
end

endmodule

module main_driver(
        
);
    // Instantiate the clock_handler module
    clock_handler clock_module (
        .clk(clk),
        .AM_PM(AM_PM),
        .set_time(set_time),
        .input_sec(input_sec),
        .input_min(input_min),
        .input_hour(input_hour),
        .current_24_sec(current_24_sec),
        .current_24_min(current_24_min),
        .current_24_hour(current_24_hour),
        .display_sec(display_sec),
        .display_min(display_min),
        .display_hour(display_hour),
        .is_pm(is_pm)
    );

    // Instantiate the date_handler module
    date_handler date_module (
        .clk(clk),
        .reset(reset),
        .set_date(set_date),
        .input_day(input_day),
        .input_month(input_month),
        .input_year(input_year),
        .current_24_hour(current_24_hour),
        .current_24_min(current_24_min),
        .current_24_sec(current_24_sec),
        .current_day(current_day),
        .current_month(current_month),
        .current_year(current_year)
    );

    // Instantiate the timer_handler module
    timer_handler timer_module (
        .clk(clk),
        .reset(reset),
        .set_timer(set_timer),
        .start_timer(start_timer),
        .stop_timer(stop_timer),
        .input_min(timer_input_min),
        .input_sec(timer_input_sec),
        .timer_min(timer_min),
        .timer_sec(timer_sec),
        .timer_running(timer_running),
        .timer_done(timer_done)
    );

    // Instantiate the alarm_handler module
    alarm_handler alarm_module (
        .clk(clk),
        .input_sec(current_24_sec),
        .input_min(current_24_min),
        .input_hour(current_24_hour),
        .alarm_time_sec(alarm_time_sec),
        .alarm_time_min(alarm_time_min),
        .alarm_time_hour(alarm_time_hour),
        .alarm_sound(alarm_sound)
    );

endmodule

main_tb.v
`timescale 1s/1ms

module digital_clock_tb;
    // Clock and reset signals
    reg clk;
    reg reset;

    // Clock time control signals
    reg set_time;
    reg [7:0] input_sec;
    reg [7:0] input_min;
    reg [7:0] input_hour;
    reg AM_PM;

    // Date control signals
    reg set_date;
    reg [7:0] input_day;
    reg [7:0] input_month;
    reg [15:0] input_year;

    // Timer control signals
    reg set_timer;
    reg start_timer;
    reg stop_timer;
    reg [7:0] timer_input_min;
    reg [7:0] timer_input_sec;

    // Alarm control signals
    reg [7:0] alarm_time_sec;
    reg [7:0] alarm_time_min;
    reg [7:0] alarm_time_hour;

    // Clock time outputs
    wire [7:0] current_24_sec;
    wire [7:0] current_24_min;
    wire [7:0] current_24_hour;
    wire [7:0] display_sec;
    wire [7:0] display_min;
    wire [7:0] display_hour;
    wire is_pm;

    // Date outputs
    wire [7:0] current_day;
    wire [7:0] current_month;
    wire [15:0] current_year;

    // Timer outputs
    wire [7:0] timer_min;
    wire [7:0] timer_sec;
    wire timer_running;
    wire timer_done;

    // Alarm outputs
    wire alarm_sound;

    // Display variables for monitoring
    reg [7:0] display_seconds;
    reg [7:0] display_minutes;
    reg [7:0] display_hours;

    // Indicator to display am or pm on the screen
    reg [15:0] am_pm_indicator;

    // Instantiate the clock_handler module
    clock_handler clock_module (
        .clk(clk),
        .AM_PM(AM_PM),
        .set_time(set_time),
        .input_sec(input_sec),
        .input_min(input_min),
        .input_hour(input_hour),
        .current_24_sec(current_24_sec),
        .current_24_min(current_24_min),
        .current_24_hour(current_24_hour),
        .display_sec(display_sec),
        .display_min(display_min),
        .display_hour(display_hour),
        .is_pm(is_pm)
    );

    // Instantiate the date_handler module
    date_handler date_module (
        .clk(clk),
        .reset(reset),
        .set_date(set_date),
        .input_day(input_day),
        .input_month(input_month),
        .input_year(input_year),
        .current_24_hour(current_24_hour),
        .current_24_min(current_24_min),
        .current_24_sec(current_24_sec),
        .current_day(current_day),
        .current_month(current_month),
        .current_year(current_year)
    );

    // Instantiate the timer_handler module
    timer_handler timer_module (
        .clk(clk),
        .reset(reset),
        .set_timer(set_timer),
        .start_timer(start_timer),
        .stop_timer(stop_timer),
        .input_min(timer_input_min),
        .input_sec(timer_input_sec),
        .timer_min(timer_min),
        .timer_sec(timer_sec),
        .timer_running(timer_running),
        .timer_done(timer_done)
    );

    // Instantiate the alarm_handler module
    alarm_handler alarm_module (
        .clk(clk),
        .input_sec(current_24_sec),
        .input_min(current_24_min),
        .input_hour(current_24_hour),
        .alarm_time_sec(alarm_time_sec),
        .alarm_time_min(alarm_time_min),
        .alarm_time_hour(alarm_time_hour),
        .alarm_sound(alarm_sound)
    );

    // Clock generation
    initial begin
        clk = 0;
        forever #0.5 clk = ~clk;
    end

    // Display logic - show timer when running, otherwise show clock
    always @(*) begin
        if (timer_running) begin
            display_seconds = timer_sec;
            display_minutes = timer_min;
            display_hours = 8'd0; // Timer doesn't use hours
        end else begin
            display_seconds = display_sec;
            display_minutes = display_min;
            display_hours = display_hour;
        end

        if (AM_PM) begin
            if (is_pm)
                am_pm_indicator = {"P", "M"};  // 'P' = 8'h50, 'M' = 8'h4D
            else
                am_pm_indicator = {"A", "M"};  // 'A' = 8'h41, 'M' = 8'h4D
        end else begin
            am_pm_indicator = "  ";  // Two spaces if 24-hour
        end
    end

    // Test sequence
    initial begin
        // Initialize all inputs
        reset = 1;
        set_time = 0;
        input_sec = 0;
        input_min = 0;
        input_hour = 0;
        AM_PM = 0;
        set_date = 0;
        input_day = 1;
        input_month = 1;
        input_year = 2025;
        set_timer = 0;
        start_timer = 0;
        stop_timer = 0;
        timer_input_min = 0;
        timer_input_sec = 0;
        alarm_time_sec = 0;
        alarm_time_min = 0;
        alarm_time_hour = 0;

        // Apply reset for 20ns
        #20 reset = 0;

        // Test 1: Set the time to 23:59:50
        #10;
        set_time = 1;
        input_sec = 50;
        input_min = 59;
        input_hour = 23;
        #10;
        set_time = 0;

        // Test 2: Set the date to December 31, 2025
        #10;
        set_date = 1;
        input_day = 31;
        input_month = 12;
        input_year = 2025;
        #10; set_date = 0;

        // Test 3: Set an alarm for 00:00:00
        alarm_time_sec = 0;
        alarm_time_min = 1;
        alarm_time_hour = 0;

        // Test 4: Set and start a 10-second timer
        #10;
        set_timer = 1;
        timer_input_min = 0;
        timer_input_sec = 10;
        #10;
        set_timer = 0;
        #10;
        start_timer = 1;
        #10;
        start_timer = 0;

        // Wait for the timer to run for a bit
        #200;

        // Test 5: Stop the timer
        stop_timer = 1;
        #10;
        stop_timer = 0;

        // Test 6: Wait for the clock to roll over to the next day
        // We'll speed up time by setting it closer to midnight
        #10;
        set_time = 1;
        input_sec = 58;
        input_min = 59;
        input_hour = 23;
        #10;
        set_time = 0;

        // Wait for date to change (about 30 seconds in simulation time)
        #300;

        // Test 7: Switch to 12-hour format
        AM_PM = 1;
        #100;

        // Test 8: Set a new timer and let it complete
        #10;
        set_timer = 1;
        timer_input_min = 0;
        timer_input_sec = 5; // 5-second timer
        #10;
        set_timer = 0;
        #10;
        start_timer = 1;
        #10;
        start_timer = 0;

        // Wait for the timer to finish
        #600;

        // End simulation
        #100 $finish;
    end

    /*
    // Monitor outputs
    initial begin
        $monitor("Time: %3d | Clock: %02d:%02d:%02d | Display: %02d:%02d:%02d | Date: %02d/%02d/%4d | Timer: %02d:%02d (Running: %b, Done: %b) | Alarm: %b",
            $time,
            current_24_hour, current_24_min, current_24_sec,
            display_hours, display_minutes, display_seconds,
            current_day, current_month, current_year,
            timer_min, timer_sec, timer_running, timer_done,
            alarm_sound);
    end

    initial begin
        $monitor("Time: %3d | Clock: %02d:%02d:%02d | Display: %02d:%02d:%02d | Date: %02d/%02d/%4d | Timer: %02d:%02d (Running: %b, Done: %b) | Alarm: %b\n set_time: %b | set_date: %b | set_timer: %b | start_timer: %b | stop_timer: %b | AM_PM: %b | input_sec: %d | input_min: %d | input_hour: %d | input_day: %d\ninput_month: %d | input_year: %d | timer_input_min: %d | timer_input_sec: %d | alarm_time_sec: %d | alarm_time_min: %d | alarm_time_hour: %d | reset: %b",
            $time,
            current_24_hour, current_24_min, current_24_sec,
            display_hours, display_minutes, display_seconds,
            current_day, current_month, current_year,
            timer_min, timer_sec, timer_running, timer_done,
            alarm_sound,
            set_time, set_date, set_timer, start_timer, stop_timer, AM_PM,
            input_sec, input_min, input_hour, input_day, input_month, input_year,
            timer_input_min, timer_input_sec,
            alarm_time_sec, alarm_time_min, alarm_time_hour,
            reset);
    end

    */


   initial begin
       $monitor("Time: %3d | Clock: %02d:%02d:%02d | Display: %02d:%02d:%02d %c%c | Date: %02d/%02d/%4d\nTimer: %02d:%02d (Running: %b, Done: %b) | Alarm: %b\nControls: set_time=%b | set_date=%b | set_timer=%b | start=%b | stop=%b | AM_PM=%b | reset=%b\nInputs: sec=%d, min=%d, hour=%d, day=%d, month=%d, year=%d,\nTimer: min=%d, sec=%d | Alarm: sec=%d, min=%d, hour=%d\n",
           $time,
           current_24_hour, current_24_min, current_24_sec,
           display_hours, display_minutes, display_seconds,
           am_pm_indicator[15:8], am_pm_indicator[7:0],
           current_day, current_month, current_year,
           timer_min, timer_sec, timer_running, timer_done,
           alarm_sound,
           set_time, set_date, set_timer, start_timer, stop_timer, AM_PM, reset,
           input_sec, input_min, input_hour, input_day, input_month, input_year,
           timer_input_min, timer_input_sec,
           alarm_time_sec, alarm_time_min, alarm_time_hour);
   end

   initial begin
       // Check for syntax errors in the alarm_handler module
       $dumpfile("wave.vcd");
       $dumpvars(0, digital_clock_tb);
   end

endmodule

wave.vcd
$date
	Sun May  4 17:24:21 2025
$end
$version
	Icarus Verilog
$end
$timescale
	1ms
$end
$scope module digital_clock_tb $end
$var wire 8 ! timer_sec [7:0] $end
$var wire 1 " timer_running $end
$var wire 8 # timer_min [7:0] $end
$var wire 1 $ timer_done $end
$var wire 1 % is_pm $end
$var wire 8 & display_sec [7:0] $end
$var wire 8 ' display_min [7:0] $end
$var wire 8 ( display_hour [7:0] $end
$var wire 16 ) current_year [15:0] $end
$var wire 8 * current_month [7:0] $end
$var wire 8 + current_day [7:0] $end
$var wire 8 , current_24_sec [7:0] $end
$var wire 8 - current_24_min [7:0] $end
$var wire 8 . current_24_hour [7:0] $end
$var wire 1 / alarm_sound $end
$var reg 1 0 AM_PM $end
$var reg 8 1 alarm_time_hour [7:0] $end
$var reg 8 2 alarm_time_min [7:0] $end
$var reg 8 3 alarm_time_sec [7:0] $end
$var reg 16 4 am_pm_indicator [15:0] $end
$var reg 1 5 clk $end
$var reg 8 6 display_hours [7:0] $end
$var reg 8 7 display_minutes [7:0] $end
$var reg 8 8 display_seconds [7:0] $end
$var reg 8 9 input_day [7:0] $end
$var reg 8 : input_hour [7:0] $end
$var reg 8 ; input_min [7:0] $end
$var reg 8 < input_month [7:0] $end
$var reg 8 = input_sec [7:0] $end
$var reg 16 > input_year [15:0] $end
$var reg 1 ? reset $end
$var reg 1 @ set_date $end
$var reg 1 A set_time $end
$var reg 1 B set_timer $end
$var reg 1 C start_timer $end
$var reg 1 D stop_timer $end
$var reg 8 E timer_input_min [7:0] $end
$var reg 8 F timer_input_sec [7:0] $end
$scope module alarm_module $end
$var wire 8 G alarm_time_hour [7:0] $end
$var wire 8 H alarm_time_min [7:0] $end
$var wire 8 I alarm_time_sec [7:0] $end
$var wire 1 5 clk $end
$var wire 8 J input_sec [7:0] $end
$var wire 8 K input_min [7:0] $end
$var wire 8 L input_hour [7:0] $end
$var reg 1 / alarm_sound $end
$upscope $end
$scope module clock_module $end
$var wire 1 0 AM_PM $end
$var wire 1 5 clk $end
$var wire 8 M input_hour [7:0] $end
$var wire 8 N input_min [7:0] $end
$var wire 8 O input_sec [7:0] $end
$var wire 1 A set_time $end
$var reg 8 P current_24_hour [7:0] $end
$var reg 8 Q current_24_min [7:0] $end
$var reg 8 R current_24_sec [7:0] $end
$var reg 8 S display_hour [7:0] $end
$var reg 8 T display_min [7:0] $end
$var reg 8 U display_sec [7:0] $end
$var reg 1 % is_pm $end
$upscope $end
$scope module date_module $end
$var wire 1 5 clk $end
$var wire 8 V current_24_hour [7:0] $end
$var wire 8 W current_24_min [7:0] $end
$var wire 8 X current_24_sec [7:0] $end
$var wire 8 Y input_day [7:0] $end
$var wire 8 Z input_month [7:0] $end
$var wire 16 [ input_year [15:0] $end
$var wire 1 ? reset $end
$var wire 1 @ set_date $end
$var reg 8 \ current_day [7:0] $end
$var reg 8 ] current_month [7:0] $end
$var reg 16 ^ current_year [15:0] $end
$var reg 8 _ days_in_current_month [7:0] $end
$upscope $end
$scope module timer_module $end
$var wire 1 5 clk $end
$var wire 8 ` input_min [7:0] $end
$var wire 8 a input_sec [7:0] $end
$var wire 1 ? reset $end
$var wire 1 B set_timer $end
$var wire 1 C start_timer $end
$var wire 1 D stop_timer $end
$var reg 8 b max_min [7:0] $end
$var reg 1 $ timer_done $end
$var reg 8 c timer_min [7:0] $end
$var reg 1 " timer_running $end
$var reg 8 d timer_sec [7:0] $end
$upscope $end
$upscope $end
$enddefinitions $end
$comment Show the parameter values. $end
$dumpall
$end
#0
$dumpvars
b0 d
b0 c
b1010 b
b0 a
b0 `
bx _
b11111101001 ^
b1 ]
b1 \
b11111101001 [
b1 Z
b1 Y
bx X
bx W
bx V
bx U
bx T
bx S
bx R
bx Q
bx P
b0 O
b0 N
b0 M
bx L
bx K
bx J
b0 I
b0 H
b0 G
b0 F
b0 E
0D
0C
0B
0A
0@
1?
b11111101001 >
b0 =
b1 <
b0 ;
b0 :
b1 9
bx 8
bx 7
bx 6
05
b10000000100000 4
b0 3
b0 2
b0 1
00
x/
bx .
bx -
bx ,
b1 +
b1 *
b11111101001 )
bx (
bx '
bx &
0%
0$
b0 #
0"
b0 !
$end
#500
0/
15
#1000
05
#1500
15
#2000
05
#2500
15
#3000
05
#3500
15
#4000
05
#4500
15
#5000
05
#5500
15
#6000
05
#6500
15
#7000
05
#7500
15
#8000
05
#8500
15
#9000
05
#9500
15
#10000
05
#10500
15
#11000
05
#11500
15
#12000
05
#12500
15
#13000
05
#13500
15
#14000
05
#14500
15
#15000
05
#15500
15
#16000
05
#16500
15
#17000
05
#17500
15
#18000
05
#18500
15
#19000
05
#19500
15
#20000
05
0?
#20500
15
#21000
05
#21500
15
#22000
05
#22500
15
#23000
05
#23500
15
#24000
05
#24500
15
#25000
05
#25500
15
#26000
05
#26500
15
#27000
05
#27500
15
#28000
05
#28500
15
#29000
05
#29500
15
#30000
05
b10111 :
b10111 M
b111011 ;
b111011 N
b110010 =
b110010 O
1A
#30500
b10111 6
b111011 7
b110010 8
b10111 (
b10111 S
b111011 '
b111011 T
b110010 &
b110010 U
b10111 .
b10111 L
b10111 P
b10111 V
b111011 -
b111011 K
b111011 Q
b111011 W
b110010 ,
b110010 J
b110010 R
b110010 X
15
#31000
05
#31500
15
#32000
05
#32500
15
#33000
05
#33500
15
#34000
05
#34500
15
#35000
05
#35500
15
#36000
05
#36500
15
#37000
05
#37500
15
#38000
05
#38500
15
#39000
05
#39500
15
#40000
05
0A
#40500
b110011 8
b110011 &
b110011 U
b110011 ,
b110011 J
b110011 R
b110011 X
15
#41000
05
#41500
b110100 8
b110100 &
b110100 U
b110100 ,
b110100 J
b110100 R
b110100 X
15
#42000
05
#42500
b110101 8
b110101 &
b110101 U
b110101 ,
b110101 J
b110101 R
b110101 X
15
#43000
05
#43500
b110110 8
b110110 &
b110110 U
b110110 ,
b110110 J
b110110 R
b110110 X
15
#44000
05
#44500
b110111 8
b110111 &
b110111 U
b110111 ,
b110111 J
b110111 R
b110111 X
15
#45000
05
#45500
b111000 8
b111000 &
b111000 U
b111000 ,
b111000 J
b111000 R
b111000 X
15
#46000
05
#46500
b111001 8
b111001 &
b111001 U
b111001 ,
b111001 J
b111001 R
b111001 X
15
#47000
05
#47500
b111010 8
b111010 &
b111010 U
b111010 ,
b111010 J
b111010 R
b111010 X
15
#48000
05
#48500
b111011 8
b111011 &
b111011 U
b111011 ,
b111011 J
b111011 R
b111011 X
15
#49000
05
#49500
b0 6
b0 7
b0 8
b0 (
b0 S
b0 '
b0 T
b0 &
b0 U
b0 .
b0 L
b0 P
b0 V
b0 -
b0 K
b0 Q
b0 W
b0 ,
b0 J
b0 R
b0 X
b10 +
b10 \
b11111 _
15
#50000
05
b1100 <
b1100 Z
b11111 9
b11111 Y
1@
#50500
b1 8
b1 &
b1 U
b1 ,
b1 J
b1 R
b1 X
1/
b1100 *
b1100 ]
b11111 +
b11111 \
15
#51000
05
#51500
b10 8
b10 &
b10 U
0/
b10 ,
b10 J
b10 R
b10 X
15
#52000
05
#52500
b11 8
b11 &
b11 U
b11 ,
b11 J
b11 R
b11 X
15
#53000
05
#53500
b100 8
b100 &
b100 U
b100 ,
b100 J
b100 R
b100 X
15
#54000
05
#54500
b101 8
b101 &
b101 U
b101 ,
b101 J
b101 R
b101 X
15
#55000
05
#55500
b110 8
b110 &
b110 U
b110 ,
b110 J
b110 R
b110 X
15
#56000
05
#56500
b111 8
b111 &
b111 U
b111 ,
b111 J
b111 R
b111 X
15
#57000
05
#57500
b1000 8
b1000 &
b1000 U
b1000 ,
b1000 J
b1000 R
b1000 X
15
#58000
05
#58500
b1001 8
b1001 &
b1001 U
b1001 ,
b1001 J
b1001 R
b1001 X
15
#59000
05
#59500
b1010 8
b1010 &
b1010 U
b1010 ,
b1010 J
b1010 R
b1010 X
15
#60000
05
b1 2
b1 H
0@
#60500
b1011 8
b1011 &
b1011 U
b1011 ,
b1011 J
b1011 R
b1011 X
15
#61000
05
#61500
b1100 8
b1100 &
b1100 U
b1100 ,
b1100 J
b1100 R
b1100 X
15
#62000
05
#62500
b1101 8
b1101 &
b1101 U
b1101 ,
b1101 J
b1101 R
b1101 X
15
#63000
05
#63500
b1110 8
b1110 &
b1110 U
b1110 ,
b1110 J
b1110 R
b1110 X
15
#64000
05
#64500
b1111 8
b1111 &
b1111 U
b1111 ,
b1111 J
b1111 R
b1111 X
15
#65000
05
#65500
b10000 8
b10000 &
b10000 U
b10000 ,
b10000 J
b10000 R
b10000 X
15
#66000
05
#66500
b10001 8
b10001 &
b10001 U
b10001 ,
b10001 J
b10001 R
b10001 X
15
#67000
05
#67500
b10010 8
b10010 &
b10010 U
b10010 ,
b10010 J
b10010 R
b10010 X
15
#68000
05
#68500
b10011 8
b10011 &
b10011 U
b10011 ,
b10011 J
b10011 R
b10011 X
15
#69000
05
#69500
b10100 8
b10100 &
b10100 U
b10100 ,
b10100 J
b10100 R
b10100 X
15
#70000
05
b1010 F
b1010 a
1B
#70500
b10101 8
b10101 &
b10101 U
b10101 ,
b10101 J
b10101 R
b10101 X
b1010 !
b1010 d
15
#71000
05
#71500
b10110 8
b10110 &
b10110 U
b10110 ,
b10110 J
b10110 R
b10110 X
15
#72000
05
#72500
b10111 8
b10111 &
b10111 U
b10111 ,
b10111 J
b10111 R
b10111 X
15
#73000
05
#73500
b11000 8
b11000 &
b11000 U
b11000 ,
b11000 J
b11000 R
b11000 X
15
#74000
05
#74500
b11001 8
b11001 &
b11001 U
b11001 ,
b11001 J
b11001 R
b11001 X
15
#75000
05
#75500
b11010 8
b11010 &
b11010 U
b11010 ,
b11010 J
b11010 R
b11010 X
15
#76000
05
#76500
b11011 8
b11011 &
b11011 U
b11011 ,
b11011 J
b11011 R
b11011 X
15
#77000
05
#77500
b11100 8
b11100 &
b11100 U
b11100 ,
b11100 J
b11100 R
b11100 X
15
#78000
05
#78500
b11101 8
b11101 &
b11101 U
b11101 ,
b11101 J
b11101 R
b11101 X
15
#79000
05
#79500
b11110 8
b11110 &
b11110 U
b11110 ,
b11110 J
b11110 R
b11110 X
15
#80000
05
0B
#80500
b11111 8
b11111 &
b11111 U
b11111 ,
b11111 J
b11111 R
b11111 X
15
#81000
05
#81500
b100000 8
b100000 &
b100000 U
b100000 ,
b100000 J
b100000 R
b100000 X
15
#82000
05
#82500
b100001 8
b100001 &
b100001 U
b100001 ,
b100001 J
b100001 R
b100001 X
15
#83000
05
#83500
b100010 8
b100010 &
b100010 U
b100010 ,
b100010 J
b100010 R
b100010 X
15
#84000
05
#84500
b100011 8
b100011 &
b100011 U
b100011 ,
b100011 J
b100011 R
b100011 X
15
#85000
05
#85500
b100100 8
b100100 &
b100100 U
b100100 ,
b100100 J
b100100 R
b100100 X
15
#86000
05
#86500
b100101 8
b100101 &
b100101 U
b100101 ,
b100101 J
b100101 R
b100101 X
15
#87000
05
#87500
b100110 8
b100110 &
b100110 U
b100110 ,
b100110 J
b100110 R
b100110 X
15
#88000
05
#88500
b100111 8
b100111 &
b100111 U
b100111 ,
b100111 J
b100111 R
b100111 X
15
#89000
05
#89500
b101000 8
b101000 &
b101000 U
b101000 ,
b101000 J
b101000 R
b101000 X
15
#90000
05
1C
#90500
b101001 &
b101001 U
b1010 8
b101001 ,
b101001 J
b101001 R
b101001 X
1"
15
#91000
05
#91500
b101010 &
b101010 U
b1001 8
b101010 ,
b101010 J
b101010 R
b101010 X
b1001 !
b1001 d
15
#92000
05
#92500
b101011 &
b101011 U
b1000 8
b101011 ,
b101011 J
b101011 R
b101011 X
b1000 !
b1000 d
15
#93000
05
#93500
b101100 &
b101100 U
b111 8
b101100 ,
b101100 J
b101100 R
b101100 X
b111 !
b111 d
15
#94000
05
#94500
b101101 &
b101101 U
b110 8
b101101 ,
b101101 J
b101101 R
b101101 X
b110 !
b110 d
15
#95000
05
#95500
b101110 &
b101110 U
b101 8
b101110 ,
b101110 J
b101110 R
b101110 X
b101 !
b101 d
15
#96000
05
#96500
b101111 &
b101111 U
b100 8
b101111 ,
b101111 J
b101111 R
b101111 X
b100 !
b100 d
15
#97000
05
#97500
b110000 &
b110000 U
b11 8
b110000 ,
b110000 J
b110000 R
b110000 X
b11 !
b11 d
15
#98000
05
#98500
b110001 &
b110001 U
b10 8
b110001 ,
b110001 J
b110001 R
b110001 X
b10 !
b10 d
15
#99000
05
#99500
b110010 &
b110010 U
b1 8
b110010 ,
b110010 J
b110010 R
b110010 X
b1 !
b1 d
15
#100000
05
0C
#100500
b110011 &
b110011 U
b0 8
b110011 ,
b110011 J
b110011 R
b110011 X
b0 !
b0 d
15
#101000
05
#101500
b110100 &
b110100 U
b110100 8
b110100 ,
b110100 J
b110100 R
b110100 X
1$
0"
15
#102000
05
#102500
b110101 8
b110101 &
b110101 U
b110101 ,
b110101 J
b110101 R
b110101 X
15
#103000
05
#103500
b110110 8
b110110 &
b110110 U
b110110 ,
b110110 J
b110110 R
b110110 X
15
#104000
05
#104500
b110111 8
b110111 &
b110111 U
b110111 ,
b110111 J
b110111 R
b110111 X
15
#105000
05
#105500
b111000 8
b111000 &
b111000 U
b111000 ,
b111000 J
b111000 R
b111000 X
15
#106000
05
#106500
b111001 8
b111001 &
b111001 U
b111001 ,
b111001 J
b111001 R
b111001 X
15
#107000
05
#107500
b111010 8
b111010 &
b111010 U
b111010 ,
b111010 J
b111010 R
b111010 X
15
#108000
05
#108500
b111011 8
b111011 &
b111011 U
b111011 ,
b111011 J
b111011 R
b111011 X
15
#109000
05
#109500
b1 7
b0 8
b1 '
b1 T
b0 &
b0 U
b1 -
b1 K
b1 Q
b1 W
b0 ,
b0 J
b0 R
b0 X
15
#110000
05
#110500
b1 8
b1 &
b1 U
b1 ,
b1 J
b1 R
b1 X
1/
15
#111000
05
#111500
b10 8
b10 &
b10 U
0/
b10 ,
b10 J
b10 R
b10 X
15
#112000
05
#112500
b11 8
b11 &
b11 U
b11 ,
b11 J
b11 R
b11 X
15
#113000
05
#113500
b100 8
b100 &
b100 U
b100 ,
b100 J
b100 R
b100 X
15
#114000
05
#114500
b101 8
b101 &
b101 U
b101 ,
b101 J
b101 R
b101 X
15
#115000
05
#115500
b110 8
b110 &
b110 U
b110 ,
b110 J
b110 R
b110 X
15
#116000
05
#116500
b111 8
b111 &
b111 U
b111 ,
b111 J
b111 R
b111 X
15
#117000
05
#117500
b1000 8
b1000 &
b1000 U
b1000 ,
b1000 J
b1000 R
b1000 X
15
#118000
05
#118500
b1001 8
b1001 &
b1001 U
b1001 ,
b1001 J
b1001 R
b1001 X
15
#119000
05
#119500
b1010 8
b1010 &
b1010 U
b1010 ,
b1010 J
b1010 R
b1010 X
15
#120000
05
#120500
b1011 8
b1011 &
b1011 U
b1011 ,
b1011 J
b1011 R
b1011 X
15
#121000
05
#121500
b1100 8
b1100 &
b1100 U
b1100 ,
b1100 J
b1100 R
b1100 X
15
#122000
05
#122500
b1101 8
b1101 &
b1101 U
b1101 ,
b1101 J
b1101 R
b1101 X
15
#123000
05
#123500
b1110 8
b1110 &
b1110 U
b1110 ,
b1110 J
b1110 R
b1110 X
15
#124000
05
#124500
b1111 8
b1111 &
b1111 U
b1111 ,
b1111 J
b1111 R
b1111 X
15
#125000
05
#125500
b10000 8
b10000 &
b10000 U
b10000 ,
b10000 J
b10000 R
b10000 X
15
#126000
05
#126500
b10001 8
b10001 &
b10001 U
b10001 ,
b10001 J
b10001 R
b10001 X
15
#127000
05
#127500
b10010 8
b10010 &
b10010 U
b10010 ,
b10010 J
b10010 R
b10010 X
15
#128000
05
