main.v
module clock_handler (
    input clk,
    input reset,
    input set_time,
    input [7:0] input_sec,
    input [7:0] input_min,
    input [7:0] input_hour,

    output reg [7:0] current_24_sec,
    output reg [7:0] current_24_min,
    output reg [7:0] current_24_hour
);

// synchronous time set and update
always @(posedge clk or posedge reset) begin
    if (reset) begin
        current_24_sec  <= 0;
        current_24_min  <= 0;
        current_24_hour <= 0;
    end else if (set_time == 1'd1) begin
        current_24_sec  <= input_sec;
        current_24_min  <= input_min;
        current_24_hour <= input_hour;
    end else begin
        if (current_24_sec == 8'd59) begin
            current_24_sec <= 8'd0;
            if (current_24_min == 8'd59) begin
                current_24_min <= 8'd0;
                if (current_24_hour == 8'd23) begin
                    current_24_hour <= 8'd0;
                end else begin
                    current_24_hour <= current_24_hour + 1;
                end
            end else begin
                current_24_min <= current_24_min + 1;
            end
        end else begin
            current_24_sec <= current_24_sec + 1;
        end
    end
end

endmodule

module display_handler (
    input clk,
    input hour_format, // 1 for 12 hour, 0 for 24 hour format
    input timer_running,

    input [7:0] current_24_sec,
    input [7:0] current_24_min,
    input [7:0] current_24_hour,

    input [7:0] timer_min,
    input [7:0] timer_sec,

    output reg [7:0] display_sec,
    output reg [7:0] display_min,
    output reg [7:0] display_hour,
    output reg is_pm
);

// Display time in 12-hour or 24-hour format
always @(posedge clk) begin
    if(timer_running) begin
        display_sec <= timer_sec;
        display_min <= timer_min;
        display_hour <= 8'd0;

    end else begin
        display_sec <= current_24_sec;
        display_min <= current_24_min;

        if (hour_format == 1'b1) begin  // 12-hour format
            if (current_24_hour == 0) begin
                display_hour <= 8'd12;  // 12 AM (midnight)
            end else if (current_24_hour == 12) begin
                display_hour <= 8'd12;  // 12 PM (noon)
            end else if (current_24_hour > 12) begin
                display_hour <= current_24_hour - 12;  // PM hours
            end else begin
                display_hour <= current_24_hour;  // AM hours
            end
        end else begin  // 24-hour format
            display_hour <= current_24_hour;
        end

        if (hour_format == 1'b1) begin  // 12-hour format
            is_pm <= (current_24_hour >= 12) ? 1'b1 : 1'b0;
        end else begin
            is_pm <= 1'b0;  // Don't care in 24-hour mode
        end
    end
end

endmodule

module date_handler (
    input clk,
    input reset,
    input set_date,
    input [7:0] input_day,
    input [7:0] input_month,
    input [15:0] input_year,

    // Clock time inputs to detect day changes
    input [7:0] current_24_hour,
    input [7:0] current_24_min,
    input [7:0] current_24_sec,

    // Date outputs
    output reg [ 7:0] current_day,
    output reg [ 7:0] current_month,
    output reg [15:0] current_year
);

// Internal signals
reg [7:0] days_in_current_month;

// Date handling logic
always @(posedge clk or posedge reset) begin
    if (reset) begin
        // Reset to default date
        current_day   <= 8'd1;
        current_month <= 8'd1;
        current_year  <= 16'd2020;

    end else if (set_date) begin
        // Set date manually when set_date is active
        current_day   <= input_day;
        current_month <= input_month;
        current_year  <= input_year;

    end else if (current_24_hour == 8'd23 && current_24_min == 8'd59 && current_24_sec == 8'd59) begin
        // Day changes at midnight (23:59:59)

        // First determine days in current month without using a function
        case (current_month)
            8'd1, 8'd3, 8'd5, 8'd7, 8'd8, 8'd10, 8'd12:
                days_in_current_month = 8'd31;  // Jan, Mar, May, Jul, Aug, Oct, Dec

            8'd4, 8'd6, 8'd9, 8'd11: days_in_current_month = 8'd30;  // Apr, Jun, Sep, Nov

            8'd2: begin  // February
                // Check leap year
                if (((current_year % 4 == 0) && (current_year % 100 != 0)) || (current_year % 400 == 0))
                    days_in_current_month = 8'd29;  // Leap year
                else days_in_current_month = 8'd28;  // Non-leap year
            end

            default: days_in_current_month = 8'd30;  // Default case
        endcase

        // Update date
        if (current_day == days_in_current_month) begin
            current_day <= 8'd1;  // Reset day to 1

            if (current_month == 8'd12) begin
                current_month <= 8'd1;  // Reset month to January
                current_year  <= current_year + 16'd1;  // Increment year
            end else begin
                current_month <= current_month + 8'd1;  // Increment month
            end
        end else begin
            current_day <= current_day + 8'd1;  // Increment day
        end
    end
end

endmodule

module alarm_handler (
    input clk,
    input set_alarm,

    input [7:0] current_24_sec,
    input [7:0] current_24_min,
    input [7:0] current_24_hour,

    input [7:0] alarm_input_sec,
    input [7:0] alarm_input_min,
    input [7:0] alarm_input_hour,

    input snooze_alarm,
    input stop_alarm,

    output reg alarm_buzzer
);
    reg [7:0] input_sec_internal;
    reg [7:0] input_min_internal;
    reg [7:0] input_hour_internal;
    reg [9:0] counter;
    reg is_snoozed;
    reg is_buzzing;

always @(posedge clk) begin
    // Stop alarm functionality
    if(stop_alarm) begin
        is_buzzing <= 0;
        alarm_buzzer <= 0;
        counter <= 0;
    end
    // Snooze alarm functionality
    else if(snooze_alarm) begin
        is_snoozed <= 1;
        alarm_buzzer <= 0;
        is_buzzing <= 0;
        counter <= 0;
    end
    // Set alarm functionality
    else if(set_alarm) begin
        input_sec_internal <= alarm_input_sec;
        input_min_internal <= alarm_input_min;
        input_hour_internal <= alarm_input_hour;
        is_snoozed <= 0;
        alarm_buzzer <= 0;
        is_buzzing <= 0;
        counter <= 0;
    end
    // Snooze timer functionality
    else if(is_snoozed) begin
        alarm_buzzer <= 0;
        is_buzzing <= 0;
        counter <= counter + 1;
        if(counter >= 5) begin  // After snooze period (300 clock cycles)
            is_snoozed <= 0;
            alarm_buzzer <= 1;
            is_buzzing <= 1;
            counter <= 0;
        end
    end
    // Alarm matching current time
    else if ((input_sec_internal == current_24_sec &&
              input_min_internal == current_24_min &&
              input_hour_internal == current_24_hour) || is_buzzing) begin
        if(!is_buzzing) is_buzzing <= 1;
        alarm_buzzer <= 1;
    end
    // Default state - alarm not active
    else begin
        alarm_buzzer <= 0;
    end
end

endmodule

module timer_handler (
    input clk,
    input reset,
    input start_timer,
    input stop_timer,
    input set_timer,
    input [7:0] input_min,
    input [7:0] input_sec,

    output reg [7:0] timer_min,
    output reg [7:0] timer_sec,
    output reg timer_running,
    output reg timer_buzzer
);

reg [7:0] max_min = 8'd10;

always @(posedge clk or posedge reset) begin
    if (reset) begin
        timer_min <= 8'd0;
        timer_sec <= 8'd0;
        timer_running <= 1'b0;
        timer_buzzer <= 1'b0;
    end else if (set_timer) begin
        if (input_min > max_min) begin
            // Limit to maximum 10 minutes
            timer_min <= max_min;
            timer_sec <= input_sec;
        end else begin
            timer_min <= input_min;
            timer_sec <= input_sec;
        end
        timer_running <= 1'b0;
        timer_buzzer <= 1'b0;
    end else if (start_timer) begin
        timer_running <= 1'b1;
        timer_buzzer <= 1'b0;
    end else if (stop_timer) begin
        // Stop the timer
        timer_running <= 1'b0;
        timer_buzzer <= 1'b0;
    end

    if (timer_running) begin
        // Timer is running, decrement
        if (timer_sec == 8'd0) begin
            if (timer_min == 8'd0) begin
                // Timer has reached zero
                timer_running <= 1'b0;
                timer_buzzer <= 1'b1;
            end else begin
                // Decrement minute, reset seconds to 59
                timer_min <= timer_min - 8'd1;
                timer_sec <= 8'd59;
            end
        end else begin
            // Decrement seconds
            timer_sec <= timer_sec - 8'd1;
        end
    end
end

endmodule

module main_driver (
    input        clk,
    input        reset,
    input        hour_format,
    input        set_time,
    input        set_date,
    input        set_alarm,
    input        snooze_alarm,
    input        stop_alarm,
    input        set_timer,
    input        start_timer,
    input        stop_timer,

    input  [7:0] input_sec,
    input  [7:0] input_min,
    input  [7:0] input_hour,
    input  [7:0] input_day,
    input  [7:0] input_month,
    input [15:0] input_year,
    input  [7:0] timer_input_min,
    input  [7:0] timer_input_sec,
    input  [7:0] alarm_input_sec,
    input  [7:0] alarm_input_min,
    input  [7:0] alarm_input_hour,

    output [7:0] current_24_sec,
    output [7:0] current_24_min,
    output [7:0] current_24_hour,
    output [7:0] display_sec,
    output [7:0] display_min,
    output [7:0] display_hour,
    output [7:0] current_day,
    output [7:0] current_month,
    output [15:0] current_year,
    output [7:0] timer_min,
    output [7:0] timer_sec,
    output       timer_running,
    output       timer_buzzer,
    output       alarm_buzzer
);
    // Instantiate the clock_handler module
    clock_handler clock_module (
        .clk(clk),
        .reset(reset),
        .set_time(set_time),
        .input_sec(input_sec),
        .input_min(input_min),
        .input_hour(input_hour),
        .current_24_sec(current_24_sec),
        .current_24_min(current_24_min),
        .current_24_hour(current_24_hour)
    );

    // Instantiate the display_handler module
    display_handler display_module (
        .clk(clk),
        .hour_format(hour_format),
        .current_24_sec(current_24_sec),
        .current_24_min(current_24_min),
        .current_24_hour(current_24_hour),
        .timer_min(timer_min),
        .timer_sec(timer_sec),
        .timer_running(timer_running),
        .display_sec(display_sec),
        .display_min(display_min),
        .display_hour(display_hour),
        .is_pm(is_pm)
    );

    // Instantiate the date_handler module
    date_handler date_module (
        .clk(clk),
        .reset(reset),
        .set_date(set_date),
        .input_day(input_day),
        .input_month(input_month),
        .input_year(input_year),
        .current_24_hour(current_24_hour),
        .current_24_min(current_24_min),
        .current_24_sec(current_24_sec),
        .current_day(current_day),
        .current_month(current_month),
        .current_year(current_year)
    );

    // Instantiate the timer_handler module
    timer_handler timer_module (
        .clk(clk),
        .reset(reset),
        .set_timer(set_timer),
        .start_timer(start_timer),
        .stop_timer(stop_timer),
        .input_min(timer_input_min),
        .input_sec(timer_input_sec),
        .timer_min(timer_min),
        .timer_sec(timer_sec),
        .timer_running(timer_running),
        .timer_buzzer(timer_buzzer)
    );

    // Instantiate the alarm_handler module
    alarm_handler alarm_module (
        .clk(clk),
        .set_alarm(set_alarm),
        .snooze_alarm(snooze_alarm),
        .stop_alarm(stop_alarm),
        .current_24_hour(current_24_hour),
        .current_24_min(current_24_min),
        .current_24_sec(current_24_sec),
        .alarm_input_sec(alarm_input_sec),
        .alarm_input_min(alarm_input_min),
        .alarm_input_hour(alarm_input_hour),
        .alarm_buzzer(alarm_buzzer)
    );

endmodule

main_tb.v
`timescale 1s/1ms

module digital_clock_tb;
    // Clock and reset signals
    reg clk;
    reg reset;

    // Clock time control signals
    reg set_time;
    reg [7:0] input_sec;
    reg [7:0] input_min;
    reg [7:0] input_hour;
    reg hour_format;

    // Date control signals
    reg set_date;
    reg [7:0] input_day;
    reg [7:0] input_month;
    reg [15:0] input_year;

    // Timer control signals
    reg set_timer;
    reg start_timer;
    reg stop_timer;
    reg [7:0] timer_input_min;
    reg [7:0] timer_input_sec;

    // Alarm control signals
    reg set_alarm;
    reg snooze_alarm;
    reg stop_alarm;
    reg [7:0] alarm_input_sec;
    reg [7:0] alarm_input_min;
    reg [7:0] alarm_input_hour;

    // Clock time outputs
    wire [7:0] current_24_sec;
    wire [7:0] current_24_min;
    wire [7:0] current_24_hour;
    wire [7:0] display_sec;
    wire [7:0] display_min;
    wire [7:0] display_hour;
    wire is_pm;

    // Date outputs
    wire [7:0] current_day;
    wire [7:0] current_month;
    wire [15:0] current_year;

    // Timer outputs
    wire [7:0] timer_min;
    wire [7:0] timer_sec;
    wire timer_running;
    wire timer_buzzer;

    // Alarm outputs
    wire alarm_buzzer;

    // Indicator to display am or pm on the screen
    reg [15:0] am_pm_indicator;

    // Instantiating the main driver for the clock
    main_driver dut (
        .clk(clk),
        .reset(reset),
        .hour_format(hour_format),
        .set_time(set_time),
        .set_date(set_date),
        .set_alarm(set_alarm),
        .snooze_alarm(snooze_alarm),
        .stop_alarm(stop_alarm),
        .set_timer(set_timer),
        .start_timer(start_timer),
        .stop_timer(stop_timer),
        .input_sec(input_sec),
        .input_min(input_min),
        .input_hour(input_hour),
        .input_day(input_day),
        .input_month(input_month),
        .input_year(input_year),
        .timer_input_min(timer_input_min),
        .timer_input_sec(timer_input_sec),
        .alarm_input_sec(alarm_input_sec),
        .alarm_input_min(alarm_input_min),
        .alarm_input_hour(alarm_input_hour),
        .current_24_sec(current_24_sec),
        .current_24_min(current_24_min),
        .current_24_hour(current_24_hour),
        .display_sec(display_sec),
        .display_min(display_min),
        .display_hour(display_hour),
        .current_day(current_day),
        .current_month(current_month),
        .current_year(current_year),
        .timer_min(timer_min),
        .timer_sec(timer_sec),
        .timer_running(timer_running),
        .timer_buzzer(timer_buzzer),
        .alarm_buzzer(alarm_buzzer)
    );

    // Clock generation
    initial begin
        clk = 0;
        forever #0.5 clk = ~clk;
    end

    // Display logic - show timer when running, otherwise show clock
    always @(*) begin
        if (hour_format) begin
            if (is_pm)
                am_pm_indicator = {"P", "M"};  // 'P' = 8'h50, 'M' = 8'h4D
            else
                am_pm_indicator = {"A", "M"};  // 'A' = 8'h41, 'M' = 8'h4D
        end else begin
            am_pm_indicator = "  ";  // Two spaces if 24-hour
        end
    end

    // Test sequence
    initial begin
        // Initialize all inputs
        reset = 1;
        set_time = 0;
        input_sec = 0;
        input_min = 0;
        input_hour = 0;
        hour_format = 0;
        set_date = 0;
        input_day = 1;
        input_month = 1;
        input_year = 2020;
        set_alarm = 0;
        set_timer = 0;
        start_timer = 0;
        stop_timer = 0;
        timer_input_min = 0;
        timer_input_sec = 0;
        alarm_input_sec = 0;
        alarm_input_min = 0;
        alarm_input_hour = 0;
        snooze_alarm = 0;
        stop_alarm = 0;

        // Apply reset for 1s
        #1 reset = 0;

        // Test 1: Set the time to 23:59:57
        #11;
        set_time = 1;
        input_sec = 57;
        input_min = 59;
        input_hour = 23;
        #1;
        set_time = 0;

        // Test 2: Set the date to December 31, 2025
        #3;
        set_date = 1;
        input_day = 31;
        input_month = 12;
        input_year = 2025;
        #1; set_date = 0;

        // Test 3: Set an alarm for 00:00:07
        set_alarm = 1;
        #1;
        alarm_input_sec = 7;
        alarm_input_min = 0;
        alarm_input_hour = 0;
        #1;
        set_alarm = 0;

        #5 snooze_alarm = 1;
        #1 snooze_alarm = 0;
        #7 stop_alarm = 1;
        #1 stop_alarm = 0;

        // Test 4: Set and start a 10-second timer
        #1;
        set_timer = 1;
        timer_input_min = 0;
        timer_input_sec = 10;
        #1;
        set_timer = 0;
        #1;
        start_timer = 1;
        #12;
        start_timer = 0;
        #1;
        stop_timer = 1;
        #1;
        stop_timer = 0;

        // Test 6: Wait for the clock to roll over to the next day
        // We'll speed up time by setting it closer to midnight
        #1;
        set_time = 1;
        input_sec = 58;
        input_min = 59;
        input_hour = 23;
        #1;
        set_time = 0;
        #5;

        // Test 7: Switch to 12-hour format
        hour_format = 1;

        // End simulation
        #1 $finish;
    end

   // Monitor outputs
   initial begin
       $monitor("DISPLAY: %02d:%02d:%02d %c%c | DATE: %02d/%02d/%4d\nTime: %3ds | Clock: %02d:%02d:%02d\nTimer: %02d:%02d (Running: %b, Done: %b)\nAlarm Buzzer: %0d | Alarm: %02d:%02d:%02d | Snooze = %0d | Stop Alarm = %0d\nControls: set_time=%b, set_date=%b, set_timer=%b, start_timer=%b, stop_timer=%b, set_alarm=%b, hour_format=%b, reset=%b\nInputs: sec=%d, min=%d, hour=%d, day=%d, month=%d, year=%d\nTimer Inputs: min=%d, sec=%d\n",
           display_hour, display_min, display_sec,
           am_pm_indicator[15:8], am_pm_indicator[7:0],
           current_day, current_month, current_year,
           $time,
           current_24_hour, current_24_min, current_24_sec,
           timer_min, timer_sec, timer_running, timer_buzzer,
           alarm_buzzer, alarm_input_hour, alarm_input_min, alarm_input_sec, snooze_alarm, stop_alarm,
           set_time, set_date, set_timer, start_timer, stop_timer, set_alarm, hour_format, reset,
           input_sec, input_min, input_hour, input_day, input_month, input_year,
           timer_input_min, timer_input_sec,);
   end

   initial begin
       $dumpfile("wave.vcd");
       $dumpvars(0, digital_clock_tb);
   end

endmodule

wave.vcd
$date
	Wed May  7 18:40:24 2025
$end
$version
	Icarus Verilog
$end
$timescale
	1ms
$end
$scope module digital_clock_tb $end
$var wire 1 ! is_pm $end
$var wire 8 " timer_sec [7:0] $end
$var wire 1 # timer_running $end
$var wire 8 $ timer_min [7:0] $end
$var wire 1 % timer_buzzer $end
$var wire 8 & display_sec [7:0] $end
$var wire 8 ' display_min [7:0] $end
$var wire 8 ( display_hour [7:0] $end
$var wire 16 ) current_year [15:0] $end
$var wire 8 * current_month [7:0] $end
$var wire 8 + current_day [7:0] $end
$var wire 8 , current_24_sec [7:0] $end
$var wire 8 - current_24_min [7:0] $end
$var wire 8 . current_24_hour [7:0] $end
$var wire 1 / alarm_buzzer $end
$var reg 8 0 alarm_input_hour [7:0] $end
$var reg 8 1 alarm_input_min [7:0] $end
$var reg 8 2 alarm_input_sec [7:0] $end
$var reg 16 3 am_pm_indicator [15:0] $end
$var reg 1 4 clk $end
$var reg 1 5 hour_format $end
$var reg 8 6 input_day [7:0] $end
$var reg 8 7 input_hour [7:0] $end
$var reg 8 8 input_min [7:0] $end
$var reg 8 9 input_month [7:0] $end
$var reg 8 : input_sec [7:0] $end
$var reg 16 ; input_year [15:0] $end
$var reg 1 < reset $end
$var reg 1 = set_alarm $end
$var reg 1 > set_date $end
$var reg 1 ? set_time $end
$var reg 1 @ set_timer $end
$var reg 1 A snooze_alarm $end
$var reg 1 B start_timer $end
$var reg 1 C stop_alarm $end
$var reg 1 D stop_timer $end
$var reg 8 E timer_input_min [7:0] $end
$var reg 8 F timer_input_sec [7:0] $end
$scope module dut $end
$var wire 8 G alarm_input_hour [7:0] $end
$var wire 8 H alarm_input_min [7:0] $end
$var wire 8 I alarm_input_sec [7:0] $end
$var wire 1 4 clk $end
$var wire 1 5 hour_format $end
$var wire 8 J input_day [7:0] $end
$var wire 8 K input_hour [7:0] $end
$var wire 8 L input_min [7:0] $end
$var wire 8 M input_month [7:0] $end
$var wire 8 N input_sec [7:0] $end
$var wire 16 O input_year [15:0] $end
$var wire 1 < reset $end
$var wire 1 = set_alarm $end
$var wire 1 > set_date $end
$var wire 1 ? set_time $end
$var wire 1 @ set_timer $end
$var wire 1 A snooze_alarm $end
$var wire 1 B start_timer $end
$var wire 1 C stop_alarm $end
$var wire 1 D stop_timer $end
$var wire 8 P timer_input_min [7:0] $end
$var wire 8 Q timer_input_sec [7:0] $end
$var wire 8 R timer_sec [7:0] $end
$var wire 1 # timer_running $end
$var wire 8 S timer_min [7:0] $end
$var wire 1 % timer_buzzer $end
$var wire 1 T is_pm $end
$var wire 8 U display_sec [7:0] $end
$var wire 8 V display_min [7:0] $end
$var wire 8 W display_hour [7:0] $end
$var wire 16 X current_year [15:0] $end
$var wire 8 Y current_month [7:0] $end
$var wire 8 Z current_day [7:0] $end
$var wire 8 [ current_24_sec [7:0] $end
$var wire 8 \ current_24_min [7:0] $end
$var wire 8 ] current_24_hour [7:0] $end
$var wire 1 / alarm_buzzer $end
$scope module alarm_module $end
$var wire 8 ^ alarm_input_hour [7:0] $end
$var wire 8 _ alarm_input_min [7:0] $end
$var wire 8 ` alarm_input_sec [7:0] $end
$var wire 1 4 clk $end
$var wire 1 = set_alarm $end
$var wire 1 A snooze_alarm $end
$var wire 1 C stop_alarm $end
$var wire 8 a current_24_sec [7:0] $end
$var wire 8 b current_24_min [7:0] $end
$var wire 8 c current_24_hour [7:0] $end
$var reg 1 / alarm_buzzer $end
$var reg 10 d counter [9:0] $end
$var reg 8 e input_hour_internal [7:0] $end
$var reg 8 f input_min_internal [7:0] $end
$var reg 8 g input_sec_internal [7:0] $end
$var reg 1 h is_buzzing $end
$var reg 1 i is_snoozed $end
$upscope $end
$scope module clock_module $end
$var wire 1 4 clk $end
$var wire 8 j input_hour [7:0] $end
$var wire 8 k input_min [7:0] $end
$var wire 8 l input_sec [7:0] $end
$var wire 1 < reset $end
$var wire 1 ? set_time $end
$var reg 8 m current_24_hour [7:0] $end
$var reg 8 n current_24_min [7:0] $end
$var reg 8 o current_24_sec [7:0] $end
$upscope $end
$scope module date_module $end
$var wire 1 4 clk $end
$var wire 8 p current_24_hour [7:0] $end
$var wire 8 q current_24_min [7:0] $end
$var wire 8 r current_24_sec [7:0] $end
$var wire 8 s input_day [7:0] $end
$var wire 8 t input_month [7:0] $end
$var wire 16 u input_year [15:0] $end
$var wire 1 < reset $end
$var wire 1 > set_date $end
$var reg 8 v current_day [7:0] $end
$var reg 8 w current_month [7:0] $end
$var reg 16 x current_year [15:0] $end
$var reg 8 y days_in_current_month [7:0] $end
$upscope $end
$scope module display_module $end
$var wire 1 4 clk $end
$var wire 8 z current_24_hour [7:0] $end
$var wire 8 { current_24_min [7:0] $end
$var wire 8 | current_24_sec [7:0] $end
$var wire 1 5 hour_format $end
$var wire 8 } timer_sec [7:0] $end
$var wire 1 # timer_running $end
$var wire 8 ~ timer_min [7:0] $end
$var reg 8 !" display_hour [7:0] $end
$var reg 8 "" display_min [7:0] $end
$var reg 8 #" display_sec [7:0] $end
$var reg 1 T is_pm $end
$upscope $end
$scope module timer_module $end
$var wire 1 4 clk $end
$var wire 8 $" input_min [7:0] $end
$var wire 8 %" input_sec [7:0] $end
$var wire 1 < reset $end
$var wire 1 @ set_timer $end
$var wire 1 B start_timer $end
$var wire 1 D stop_timer $end
$var reg 8 &" max_min [7:0] $end
$var reg 1 % timer_buzzer $end
$var reg 8 '" timer_min [7:0] $end
$var reg 1 # timer_running $end
$var reg 8 (" timer_sec [7:0] $end
$upscope $end
$upscope $end
$upscope $end
$enddefinitions $end
$comment Show the parameter values. $end
$dumpall
$end
#0
$dumpvars
b0 ("
b0 '"
b1010 &"
b0 %"
b0 $"
bx #"
bx ""
bx !"
b0 ~
b0 }
b0 |
b0 {
b0 z
bx y
b11111100100 x
b1 w
b1 v
b11111100100 u
b1 t
b1 s
b0 r
b0 q
b0 p
b0 o
b0 n
b0 m
b0 l
b0 k
b0 j
xi
xh
bx g
bx f
bx e
bx d
b0 c
b0 b
b0 a
b0 `
b0 _
b0 ^
b0 ]
b0 \
b0 [
b1 Z
b1 Y
b11111100100 X
bx W
bx V
bx U
xT
b0 S
b0 R
b0 Q
b0 P
b11111100100 O
b0 N
b1 M
b0 L
b0 K
b1 J
b0 I
b0 H
b0 G
b0 F
b0 E
0D
0C
0B
0A
0@
0?
0>
0=
1<
b11111100100 ;
b0 :
b1 9
b0 8
b0 7
b1 6
05
04
b10000000100000 3
b0 2
b0 1
b0 0
x/
b0 .
b0 -
b0 ,
b1 +
b1 *
b11111100100 )
bx (
bx '
bx &
0%
b0 $
0#
b0 "
z!
$end
#500
0T
b0 (
b0 W
b0 !"
b0 '
b0 V
b0 ""
b0 &
b0 U
b0 #"
0/
14
#1000
04
0<
#1500
b1 ,
b1 [
b1 a
b1 o
b1 r
b1 |
14
#2000
04
#2500
b1 &
b1 U
b1 #"
b10 ,
b10 [
b10 a
b10 o
b10 r
b10 |
14
#3000
04
#3500
b10 &
b10 U
b10 #"
b11 ,
b11 [
b11 a
b11 o
b11 r
b11 |
14
#4000
04
#4500
b11 &
b11 U
b11 #"
b100 ,
b100 [
b100 a
b100 o
b100 r
b100 |
14
#5000
04
#5500
b100 &
b100 U
b100 #"
b101 ,
b101 [
b101 a
b101 o
b101 r
b101 |
14
#6000
04
#6500
b101 &
b101 U
b101 #"
b110 ,
b110 [
b110 a
b110 o
b110 r
b110 |
14
#7000
04
#7500
b110 &
b110 U
b110 #"
b111 ,
b111 [
b111 a
b111 o
b111 r
b111 |
14
#8000
04
#8500
b111 &
b111 U
b111 #"
b1000 ,
b1000 [
b1000 a
b1000 o
b1000 r
b1000 |
14
#9000
04
#9500
b1000 &
b1000 U
b1000 #"
b1001 ,
b1001 [
b1001 a
b1001 o
b1001 r
b1001 |
14
#10000
04
#10500
b1001 &
b1001 U
b1001 #"
b1010 ,
b1010 [
b1010 a
b1010 o
b1010 r
b1010 |
14
#11000
04
#11500
b1010 &
b1010 U
b1010 #"
b1011 ,
b1011 [
b1011 a
b1011 o
b1011 r
b1011 |
14
#12000
04
b10111 7
b10111 K
b10111 j
b111011 8
b111011 L
b111011 k
b111001 :
b111001 N
b111001 l
1?
#12500
b1011 &
b1011 U
b1011 #"
b10111 .
b10111 ]
b10111 c
b10111 m
b10111 p
b10111 z
b111011 -
b111011 \
b111011 b
b111011 n
b111011 q
b111011 {
b111001 ,
b111001 [
b111001 a
b111001 o
b111001 r
b111001 |
14
#13000
04
0?
#13500
b10111 (
b10111 W
b10111 !"
b111011 '
b111011 V
b111011 ""
b111001 &
b111001 U
b111001 #"
b111010 ,
b111010 [
b111010 a
b111010 o
b111010 r
b111010 |
14
#14000
04
#14500
b111010 &
b111010 U
b111010 #"
b111011 ,
b111011 [
b111011 a
b111011 o
b111011 r
b111011 |
14
#15000
04
#15500
b111011 &
b111011 U
b111011 #"
b0 .
b0 ]
b0 c
b0 m
b0 p
b0 z
b0 -
b0 \
b0 b
b0 n
b0 q
b0 {
b0 ,
b0 [
b0 a
b0 o
b0 r
b0 |
b10 +
b10 Z
b10 v
b11111 y
14
#16000
04
b11111101001 ;
b11111101001 O
b11111101001 u
b1100 9
b1100 M
b1100 t
b11111 6
b11111 J
b11111 s
1>
#16500
b0 (
b0 W
b0 !"
b0 '
b0 V
b0 ""
b0 &
b0 U
b0 #"
b11111101001 )
b11111101001 X
b11111101001 x
b1100 *
b1100 Y
b1100 w
b11111 +
b11111 Z
b11111 v
b1 ,
b1 [
b1 a
b1 o
b1 r
b1 |
14
#17000
04
1=
0>
#17500
b0 d
0h
0i
b0 e
b0 f
b0 g
b1 &
b1 U
b1 #"
b10 ,
b10 [
b10 a
b10 o
b10 r
b10 |
14
#18000
04
b111 2
b111 I
b111 `
#18500
b10 &
b10 U
b10 #"
b111 g
b11 ,
b11 [
b11 a
b11 o
b11 r
b11 |
14
#19000
04
0=
#19500
b11 &
b11 U
b11 #"
b100 ,
b100 [
b100 a
b100 o
b100 r
b100 |
14
#20000
04
#20500
b100 &
b100 U
b100 #"
b101 ,
b101 [
b101 a
b101 o
b101 r
b101 |
14
#21000
04
#21500
b101 &
b101 U
b101 #"
b110 ,
b110 [
b110 a
b110 o
b110 r
b110 |
14
#22000
04
#22500
b110 &
b110 U
b110 #"
b111 ,
b111 [
b111 a
b111 o
b111 r
b111 |
14
#23000
04
#23500
1/
1h
b111 &
b111 U
b111 #"
b1000 ,
b1000 [
b1000 a
b1000 o
b1000 r
b1000 |
14
#24000
04
1A
#24500
b1000 &
b1000 U
b1000 #"
0h
0/
1i
b1001 ,
b1001 [
b1001 a
b1001 o
b1001 r
b1001 |
14
#25000
04
0A
#25500
b1 d
b1001 &
b1001 U
b1001 #"
b1010 ,
b1010 [
b1010 a
b1010 o
b1010 r
b1010 |
14
#26000
04
#26500
b1010 &
b1010 U
b1010 #"
b10 d
b1011 ,
b1011 [
b1011 a
b1011 o
b1011 r
b1011 |
14
#27000
04
#27500
b11 d
b1011 &
b1011 U
b1011 #"
b1100 ,
b1100 [
b1100 a
b1100 o
b1100 r
b1100 |
14
#28000
04
#28500
b1100 &
b1100 U
b1100 #"
b100 d
b1101 ,
b1101 [
b1101 a
b1101 o
b1101 r
b1101 |
14
#29000
04
#29500
b101 d
b1101 &
b1101 U
b1101 #"
b1110 ,
b1110 [
b1110 a
b1110 o
b1110 r
b1110 |
14
#30000
04
#30500
b1110 &
b1110 U
b1110 #"
1h
1/
0i
b0 d
b1111 ,
b1111 [
b1111 a
b1111 o
b1111 r
b1111 |
14
#31000
04
#31500
b1111 &
b1111 U
b1111 #"
b10000 ,
b10000 [
b10000 a
b10000 o
b10000 r
b10000 |
14
#32000
04
1C
#32500
b10000 &
b10000 U
b10000 #"
0/
0h
b10001 ,
b10001 [
b10001 a
b10001 o
b10001 r
b10001 |
14
#33000
04
0C
#33500
b10001 &
b10001 U
b10001 #"
b10010 ,
b10010 [
b10010 a
b10010 o
b10010 r
b10010 |
14
#34000
04
b1010 F
b1010 Q
b1010 %"
1@
#34500
b10010 &
b10010 U
b10010 #"
b1010 "
b1010 R
b1010 }
b1010 ("
b10011 ,
b10011 [
b10011 a
b10011 o
b10011 r
b10011 |
14
#35000
04
0@
#35500
b10011 &
b10011 U
b10011 #"
b10100 ,
b10100 [
b10100 a
b10100 o
b10100 r
b10100 |
14
#36000
04
1B
#36500
b10100 &
b10100 U
b10100 #"
1#
b10101 ,
b10101 [
b10101 a
b10101 o
b10101 r
b10101 |
14
#37000
04
#37500
b1010 &
b1010 U
b1010 #"
b10110 ,
b10110 [
b10110 a
b10110 o
b10110 r
b10110 |
b1001 "
b1001 R
b1001 }
b1001 ("
14
#38000
04
#38500
b1001 &
b1001 U
b1001 #"
b1000 "
b1000 R
b1000 }
b1000 ("
b10111 ,
b10111 [
b10111 a
b10111 o
b10111 r
b10111 |
14
#39000
04
#39500
b1000 &
b1000 U
b1000 #"
b11000 ,
b11000 [
b11000 a
b11000 o
b11000 r
b11000 |
b111 "
b111 R
b111 }
b111 ("
14
#40000
04
#40500
b111 &
b111 U
b111 #"
b110 "
b110 R
b110 }
b110 ("
b11001 ,
b11001 [
b11001 a
b11001 o
b11001 r
b11001 |
14
#41000
04
#41500
b110 &
b110 U
b110 #"
b11010 ,
b11010 [
b11010 a
b11010 o
b11010 r
b11010 |
b101 "
b101 R
b101 }
b101 ("
14
#42000
04
#42500
b101 &
b101 U
b101 #"
b100 "
b100 R
b100 }
b100 ("
b11011 ,
b11011 [
b11011 a
b11011 o
b11011 r
b11011 |
14
#43000
04
#43500
b100 &
b100 U
b100 #"
b11100 ,
b11100 [
b11100 a
b11100 o
b11100 r
b11100 |
b11 "
b11 R
b11 }
b11 ("
14
#44000
04
#44500
b11 &
b11 U
b11 #"
b10 "
b10 R
b10 }
b10 ("
b11101 ,
b11101 [
b11101 a
b11101 o
b11101 r
b11101 |
14
#45000
04
#45500
b10 &
b10 U
b10 #"
b11110 ,
b11110 [
b11110 a
b11110 o
b11110 r
b11110 |
b1 "
b1 R
b1 }
b1 ("
14
#46000
04
#46500
b1 &
b1 U
b1 #"
b0 "
b0 R
b0 }
b0 ("
b11111 ,
b11111 [
b11111 a
b11111 o
b11111 r
b11111 |
14
#47000
04
#47500
b0 &
b0 U
b0 #"
b100000 ,
b100000 [
b100000 a
b100000 o
b100000 r
b100000 |
1%
0#
14
#48000
04
0B
