main.v
module clock_handler (
    input clk,
    input reset,
    input hour_format, // 1 for 12 hour, 0 for 24 hour format
    input set_time,
    input [7:0] input_sec,
    input [7:0] input_min,
    input [7:0] input_hour,

    output reg [7:0] current_24_sec,
    output reg [7:0] current_24_min,
    output reg [7:0] current_24_hour,
    output reg [7:0] display_sec,
    output reg [7:0] display_min,
    output reg [7:0] display_hour,
    output reg is_pm
);

// synchronous time set
always @(posedge clk or posedge reset) begin
    if (reset) begin
        current_24_sec  <= 0;
        current_24_min  <= 0;
        current_24_hour <= 0;
    end else if (set_time == 1'd1) begin
        current_24_sec  <= input_sec;
        current_24_min  <= input_min;
        current_24_hour <= input_hour;
    end else begin
        if (current_24_sec == 8'd59) begin
            current_24_sec <= 8'd0;
            if (current_24_min == 8'd59) begin
                current_24_min <= 8'd0;
                if (current_24_hour == 8'd23) begin
                    current_24_hour <= 8'd0;
                end else begin
                    current_24_hour <= current_24_hour + 1;
                end
            end else begin
                current_24_min <= current_24_min + 1;
            end
        end else begin
            current_24_sec <= current_24_sec + 1;
        end
    end
end

// Display time in 12-hour or 24-hour format
always @(*) begin
    display_sec <= current_24_sec;
    display_min <= current_24_min;

    if (hour_format == 1'b1) begin  // 12-hour format
        if (current_24_hour == 0) begin
            display_hour <= 8'd12;  // 12 AM (midnight)
        end else if (current_24_hour == 12) begin
            display_hour <= 8'd12;  // 12 PM (noon)
        end else if (current_24_hour > 12) begin
            display_hour <= current_24_hour - 12;  // PM hours
        end else begin
            display_hour <= current_24_hour;  // AM hours
        end
    end else begin  // 24-hour format
        display_hour <= current_24_hour;
    end

    if (hour_format == 1'b1) begin  // 12-hour format
        is_pm <= (current_24_hour >= 12) ? 1'b1 : 1'b0;
    end else begin
        is_pm <= 1'b0;  // Don't care in 24-hour mode
    end
end

endmodule

module date_handler (
    input clk,
    input reset,
    input set_date,
    input [7:0] input_day,
    input [7:0] input_month,
    input [15:0] input_year,

    // Clock time inputs to detect day changes
    input [7:0] current_24_hour,
    input [7:0] current_24_min,
    input [7:0] current_24_sec,

    // Date outputs
    output reg [ 7:0] current_day,
    output reg [ 7:0] current_month,
    output reg [15:0] current_year
);

// Internal signals
reg [7:0] days_in_current_month;

// Date handling logic
always @(posedge clk or posedge reset) begin
    if (reset) begin
        // Reset to default date
        current_day   <= 8'd1;
        current_month <= 8'd1;
        current_year  <= 16'd2020;

    end else if (set_date) begin
        // Set date manually when set_date is active
        current_day   <= input_day;
        current_month <= input_month;
        current_year  <= input_year;

    end else if (current_24_hour == 8'd23 && current_24_min == 8'd59 && current_24_sec == 8'd59) begin
        // Day changes at midnight (23:59:59)

        // First determine days in current month without using a function
        case (current_month)
            8'd1, 8'd3, 8'd5, 8'd7, 8'd8, 8'd10, 8'd12:
                days_in_current_month = 8'd31;  // Jan, Mar, May, Jul, Aug, Oct, Dec

            8'd4, 8'd6, 8'd9, 8'd11: days_in_current_month = 8'd30;  // Apr, Jun, Sep, Nov

            8'd2: begin  // February
                // Check leap year
                if (((current_year % 4 == 0) && (current_year % 100 != 0)) || (current_year % 400 == 0))
                    days_in_current_month = 8'd29;  // Leap year
                else days_in_current_month = 8'd28;  // Non-leap year
            end

            default: days_in_current_month = 8'd30;  // Default case
        endcase

        // Update date
        if (current_day == days_in_current_month) begin
            current_day <= 8'd1;  // Reset day to 1

            if (current_month == 8'd12) begin
                current_month <= 8'd1;  // Reset month to January
                current_year  <= current_year + 16'd1;  // Increment year
            end else begin
                current_month <= current_month + 8'd1;  // Increment month
            end
        end else begin
            current_day <= current_day + 8'd1;  // Increment day
        end
    end
end

endmodule

module alarm_handler (
    input clk,
    input set_alarm,

    input [7:0] input_sec,
    input [7:0] input_min,
    input [7:0] input_hour,

    input [7:0] alarm_time_sec,
    input [7:0] alarm_time_min,
    input [7:0] alarm_time_hour,

    output reg alarm_buzzer
);
    reg [7:0] input_sec_internal;
    reg [7:0] input_min_internal;
    reg [7:0] input_hour_internal;

always @(posedge clk) begin
    if(set_alarm) begin
        input_sec_internal <= input_sec;
        input_min_internal <= input_min;
        input_hour_internal <= input_hour;
        alarm_buzzer <= 1;
    end

    if (input_sec_internal == alarm_time_sec && input_min_internal == alarm_time_min && input_hour_internal == alarm_time_hour) begin
        alarm_buzzer <= 1;
    end else begin
        alarm_buzzer <= 0;
    end
end

endmodule

module timer_handler (
    input clk,
    input reset,
    input start_timer,
    input stop_timer,
    input set_timer,
    input [7:0] input_min,
    input [7:0] input_sec,

    output reg [7:0] timer_min,
    output reg [7:0] timer_sec,
    output reg timer_running,
    output reg timer_buzzer
);


reg [7:0] max_min = 8'd10;

always @(posedge clk or posedge reset) begin
    if (reset) begin
        timer_min <= 8'd0;
        timer_sec <= 8'd0;
        timer_running <= 1'b0;
        timer_buzzer <= 1'b0;
    end else if (set_timer) begin
        if (input_min > max_min) begin
            // Limit to maximum 10 minutes
            timer_min <= max_min;
            timer_sec <= input_sec;
        end else begin
            timer_min <= input_min;
            timer_sec <= input_sec;
        end
        timer_running <= 1'b0;
        timer_buzzer <= 1'b0;
    end else if (start_timer) begin
        timer_running <= 1'b1;
        timer_buzzer <= 1'b0;
    end else if (stop_timer) begin
        // Stop the timer
        timer_running <= 1'b0;
    end

    if (timer_running) begin
        // Timer is running, decrement
        if (timer_sec == 8'd0) begin
            if (timer_min == 8'd0) begin
                // Timer has reached zero
                timer_running <= 1'b0;
                timer_buzzer <= 1'b1;
            end else begin
                // Decrement minute, reset seconds to 59
                timer_min <= timer_min - 8'd1;
                timer_sec <= 8'd59;
            end
        end else begin
            // Decrement seconds
            timer_sec <= timer_sec - 8'd1;
        end
    end
end

endmodule

module main_driver (
    input        clk,
    input        reset,
    input        hour_format,
    input        set_time,
    input        set_date,
    input        set_alarm,
    input        set_timer,
    input        start_timer,
    input        stop_timer,

    input  [7:0] input_sec,
    input  [7:0] input_min,
    input  [7:0] input_hour,
    input  [7:0] input_day,
    input  [7:0] input_month,
    input [15:0] input_year,
    input  [7:0] timer_input_min,
    input  [7:0] timer_input_sec,
    input  [7:0] alarm_time_sec,
    input  [7:0] alarm_time_min,
    input  [7:0] alarm_time_hour,

    output [7:0] current_24_sec,
    output [7:0] current_24_min,
    output [7:0] current_24_hour,
    output [7:0] display_sec,
    output [7:0] display_min,
    output [7:0] display_hour,
    output [7:0] current_day,
    output [7:0] current_month,
    output [15:0] current_year,
    output [7:0] timer_min,
    output [7:0] timer_sec,
    output       timer_running,
    output       timer_buzzer,
    output       alarm_buzzer
);
    // Instantiate the clock_handler module
    clock_handler clock_module (
        .clk(clk),
        .reset(reset),
        .hour_format(hour_format),
        .set_time(set_time),
        .input_sec(input_sec),
        .input_min(input_min),
        .input_hour(input_hour),
        .current_24_sec(current_24_sec),
        .current_24_min(current_24_min),
        .current_24_hour(current_24_hour),
        .display_sec(display_sec),
        .display_min(display_min),
        .display_hour(display_hour),
        .is_pm(is_pm)
    );

    // Instantiate the date_handler module
    date_handler date_module (
        .clk(clk),
        .reset(reset),
        .set_date(set_date),
        .input_day(input_day),
        .input_month(input_month),
        .input_year(input_year),
        .current_24_hour(current_24_hour),
        .current_24_min(current_24_min),
        .current_24_sec(current_24_sec),
        .current_day(current_day),
        .current_month(current_month),
        .current_year(current_year)
    );

    // Instantiate the timer_handler module
    timer_handler timer_module (
        .clk(clk),
        .reset(reset),
        .set_timer(set_timer),
        .start_timer(start_timer),
        .stop_timer(stop_timer),
        .input_min(timer_input_min),
        .input_sec(timer_input_sec),
        .timer_min(timer_min),
        .timer_sec(timer_sec),
        .timer_running(timer_running),
        .timer_buzzer(timer_buzzer)
    );

    // Instantiate the alarm_handler module
    alarm_handler alarm_module (
        .clk(clk),
        .set_alarm(set_alarm),
        .input_sec(current_24_sec),
        .input_min(current_24_min),
        .input_hour(current_24_hour),
        .alarm_time_sec(alarm_time_sec),
        .alarm_time_min(alarm_time_min),
        .alarm_time_hour(alarm_time_hour),
        .alarm_buzzer(alarm_buzzer)
    );

endmodule

main_tb.v
`timescale 1s/1ms

module digital_clock_tb;
    // Clock and reset signals
    reg clk;
    reg reset;

    // Clock time control signals
    reg set_time;
    reg [7:0] input_sec;
    reg [7:0] input_min;
    reg [7:0] input_hour;
    reg hour_format;

    // Date control signals
    reg set_date;
    reg [7:0] input_day;
    reg [7:0] input_month;
    reg [15:0] input_year;

    // Timer control signals
    reg set_timer;
    reg start_timer;
    reg stop_timer;
    reg [7:0] timer_input_min;
    reg [7:0] timer_input_sec;

    // Alarm control signals
    reg set_alarm;
    reg [7:0] alarm_time_sec;
    reg [7:0] alarm_time_min;
    reg [7:0] alarm_time_hour;

    // Clock time outputs
    wire [7:0] current_24_sec;
    wire [7:0] current_24_min;
    wire [7:0] current_24_hour;
    wire [7:0] display_sec;
    wire [7:0] display_min;
    wire [7:0] display_hour;
    wire is_pm;

    // Date outputs
    wire [7:0] current_day;
    wire [7:0] current_month;
    wire [15:0] current_year;

    // Timer outputs
    wire [7:0] timer_min;
    wire [7:0] timer_sec;
    wire timer_running;
    wire timer_buzzer;

    // Alarm outputs
    wire alarm_buzzer;

    // Display variables for monitoring
    reg [7:0] display_seconds;
    reg [7:0] display_minutes;
    reg [7:0] display_hours;

    // Indicator to display am or pm on the screen
    reg [15:0] am_pm_indicator;

    // Instantiating the main driver for the clock
    main_driver dut (
        .clk(clk),
        .reset(reset),
        .hour_format(hour_format),
        .set_time(set_time),
        .set_date(set_date),
        .set_alarm(set_alarm),
        .set_timer(set_timer),
        .start_timer(start_timer),
        .stop_timer(stop_timer),
        .input_sec(input_sec),
        .input_min(input_min),
        .input_hour(input_hour),
        .input_day(input_day),
        .input_month(input_month),
        .input_year(input_year),
        .timer_input_min(timer_input_min),
        .timer_input_sec(timer_input_sec),
        .alarm_time_sec(alarm_time_sec),
        .alarm_time_min(alarm_time_min),
        .alarm_time_hour(alarm_time_hour),
        .current_24_sec(current_24_sec),
        .current_24_min(current_24_min),
        .current_24_hour(current_24_hour),
        .display_sec(display_sec),
        .display_min(display_min),
        .display_hour(display_hour),
        .current_day(current_day),
        .current_month(current_month),
        .current_year(current_year),
        .timer_min(timer_min),
        .timer_sec(timer_sec),
        .timer_running(timer_running),
        .timer_buzzer(timer_buzzer),
        .alarm_buzzer(alarm_buzzer)
    );

    // Clock generation
    initial begin
        clk = 0;
        forever #0.5 clk = ~clk;
    end

    // Display logic - show timer when running, otherwise show clock
    always @(*) begin
        if (timer_running) begin
            display_seconds = timer_sec;
            display_minutes = timer_min;
            display_hours = 8'd0; // Timer doesn't use hours
        end else begin
            display_seconds = display_sec;
            display_minutes = display_min;
            display_hours = display_hour;
        end

        if (hour_format) begin
            if (is_pm)
                am_pm_indicator = {"P", "M"};  // 'P' = 8'h50, 'M' = 8'h4D
            else
                am_pm_indicator = {"A", "M"};  // 'A' = 8'h41, 'M' = 8'h4D
        end else begin
            am_pm_indicator = "  ";  // Two spaces if 24-hour
        end
    end

    // Test sequence
    initial begin
        // Initialize all inputs
        reset = 1;
        set_time = 0;
        input_sec = 0;
        input_min = 0;
        input_hour = 0;
        hour_format = 0;
        set_date = 0;
        input_day = 1;
        input_month = 1;
        input_year = 2020;
        set_alarm = 0;
        set_timer = 0;
        start_timer = 0;
        stop_timer = 0;
        timer_input_min = 0;
        timer_input_sec = 0;
        alarm_time_sec = 0;
        alarm_time_min = 0;
        alarm_time_hour = 0;

        // Apply reset for 20ns
        #20 reset = 0;

        // Test 1: Set the time to 23:59:50
        #10;
        set_time = 1;
        input_sec = 50;
        input_min = 59;
        input_hour = 23;
        #10;
        set_time = 0;

        // Test 2: Set the date to December 31, 2025
        #10;
        set_date = 1;
        input_day = 31;
        input_month = 12;
        input_year = 2025;
        #10; set_date = 0;

        // Test 3: Set an alarm for 00:01:00
        set_alarm = 1;
        alarm_time_sec = 0;
        alarm_time_min = 1;
        alarm_time_hour = 0;
        #10;
        set_alarm = 0;

        // Test 4: Set and start a 10-second timer
        #10;
        set_timer = 1;
        timer_input_min = 0;
        timer_input_sec = 10;
        #10;
        set_timer = 0;
        #10;
        start_timer = 1;
        #10;
        start_timer = 0;

        // Wait for the timer to run for a bit
        #200;

        // Test 5: Stop the timer
        stop_timer = 1;
        #10;
        stop_timer = 0;

        // Test 6: Wait for the clock to roll over to the next day
        // We'll speed up time by setting it closer to midnight
        #10;
        set_time = 1;
        input_sec = 58;
        input_min = 59;
        input_hour = 23;
        #10;
        set_time = 0;

        // Wait for date to change (about 30 seconds in simulation time)
        #300;

        // Test 7: Switch to 12-hour format
        hour_format = 1;
        #100;

        // Test 8: Set a new timer and let it complete
        #10;
        set_timer = 1;
        timer_input_min = 0;
        timer_input_sec = 5; // 5-second timer
        #10;
        set_timer = 0;
        #10;
        start_timer = 1;
        #10;
        start_timer = 0;

        // Wait for the timer to finish
        #600;

        // End simulation
        #100 $finish;
    end

   // Monitor outputs
   initial begin
       $monitor("Time: %3d | Clock: %02d:%02d:%02d | Display: %02d:%02d:%02d %c%c | Date: %02d/%02d/%4d\nTimer: %02d:%02d (Running: %b, Done: %b) | Alarm: %b\nControls: set_time=%b | set_date=%b | set_timer=%b | start=%b | stop=%b | hour_format=%b | reset=%b\nInputs: sec=%d, min=%d, hour=%d, day=%d, month=%d, year=%d,\nTimer: min=%d, sec=%d | Alarm: sec=%d, min=%d, hour=%d\n",
           $time,
           current_24_hour, current_24_min, current_24_sec,
           display_hours, display_minutes, display_seconds,
           am_pm_indicator[15:8], am_pm_indicator[7:0],
           current_day, current_month, current_year,
           timer_min, timer_sec, timer_running, timer_buzzer,
           alarm_buzzer,
           set_time, set_date, set_timer, start_timer, stop_timer, hour_format, reset,
           input_sec, input_min, input_hour, input_day, input_month, input_year,
           timer_input_min, timer_input_sec,
           alarm_time_sec, alarm_time_min, alarm_time_hour);
   end

   initial begin
       $dumpfile("wave.vcd");
       $dumpvars(0, digital_clock_tb);
   end

endmodule

wave.vcd
$date
	Sun May  4 18:22:40 2025
$end
$version
	Icarus Verilog
$end
$timescale
	1ms
$end
$scope module digital_clock_tb $end
$var wire 1 ! is_pm $end
$var wire 8 " timer_sec [7:0] $end
$var wire 1 # timer_running $end
$var wire 8 $ timer_min [7:0] $end
$var wire 1 % timer_buzzer $end
$var wire 8 & display_sec [7:0] $end
$var wire 8 ' display_min [7:0] $end
$var wire 8 ( display_hour [7:0] $end
$var wire 16 ) current_year [15:0] $end
$var wire 8 * current_month [7:0] $end
$var wire 8 + current_day [7:0] $end
$var wire 8 , current_24_sec [7:0] $end
$var wire 8 - current_24_min [7:0] $end
$var wire 8 . current_24_hour [7:0] $end
$var wire 1 / alarm_buzzer $end
$var reg 8 0 alarm_time_hour [7:0] $end
$var reg 8 1 alarm_time_min [7:0] $end
$var reg 8 2 alarm_time_sec [7:0] $end
$var reg 16 3 am_pm_indicator [15:0] $end
$var reg 1 4 clk $end
$var reg 8 5 display_hours [7:0] $end
$var reg 8 6 display_minutes [7:0] $end
$var reg 8 7 display_seconds [7:0] $end
$var reg 1 8 hour_format $end
$var reg 8 9 input_day [7:0] $end
$var reg 8 : input_hour [7:0] $end
$var reg 8 ; input_min [7:0] $end
$var reg 8 < input_month [7:0] $end
$var reg 8 = input_sec [7:0] $end
$var reg 16 > input_year [15:0] $end
$var reg 1 ? reset $end
$var reg 1 @ set_alarm $end
$var reg 1 A set_date $end
$var reg 1 B set_time $end
$var reg 1 C set_timer $end
$var reg 1 D start_timer $end
$var reg 1 E stop_timer $end
$var reg 8 F timer_input_min [7:0] $end
$var reg 8 G timer_input_sec [7:0] $end
$scope module dut $end
$var wire 8 H alarm_time_hour [7:0] $end
$var wire 8 I alarm_time_min [7:0] $end
$var wire 8 J alarm_time_sec [7:0] $end
$var wire 1 4 clk $end
$var wire 1 8 hour_format $end
$var wire 8 K input_day [7:0] $end
$var wire 8 L input_hour [7:0] $end
$var wire 8 M input_min [7:0] $end
$var wire 8 N input_month [7:0] $end
$var wire 8 O input_sec [7:0] $end
$var wire 16 P input_year [15:0] $end
$var wire 1 ? reset $end
$var wire 1 @ set_alarm $end
$var wire 1 A set_date $end
$var wire 1 B set_time $end
$var wire 1 C set_timer $end
$var wire 1 D start_timer $end
$var wire 1 E stop_timer $end
$var wire 8 Q timer_input_min [7:0] $end
$var wire 8 R timer_input_sec [7:0] $end
$var wire 8 S timer_sec [7:0] $end
$var wire 1 # timer_running $end
$var wire 8 T timer_min [7:0] $end
$var wire 1 % timer_buzzer $end
$var wire 1 U is_pm $end
$var wire 8 V display_sec [7:0] $end
$var wire 8 W display_min [7:0] $end
$var wire 8 X display_hour [7:0] $end
$var wire 16 Y current_year [15:0] $end
$var wire 8 Z current_month [7:0] $end
$var wire 8 [ current_day [7:0] $end
$var wire 8 \ current_24_sec [7:0] $end
$var wire 8 ] current_24_min [7:0] $end
$var wire 8 ^ current_24_hour [7:0] $end
$var wire 1 / alarm_buzzer $end
$scope module alarm_module $end
$var wire 8 _ alarm_time_hour [7:0] $end
$var wire 8 ` alarm_time_min [7:0] $end
$var wire 8 a alarm_time_sec [7:0] $end
$var wire 1 4 clk $end
$var wire 1 @ set_alarm $end
$var wire 8 b input_sec [7:0] $end
$var wire 8 c input_min [7:0] $end
$var wire 8 d input_hour [7:0] $end
$var reg 1 / alarm_buzzer $end
$var reg 8 e input_hour_internal [7:0] $end
$var reg 8 f input_min_internal [7:0] $end
$var reg 8 g input_sec_internal [7:0] $end
$upscope $end
$scope module clock_module $end
$var wire 1 4 clk $end
$var wire 1 8 hour_format $end
$var wire 8 h input_hour [7:0] $end
$var wire 8 i input_min [7:0] $end
$var wire 8 j input_sec [7:0] $end
$var wire 1 ? reset $end
$var wire 1 B set_time $end
$var reg 8 k current_24_hour [7:0] $end
$var reg 8 l current_24_min [7:0] $end
$var reg 8 m current_24_sec [7:0] $end
$var reg 8 n display_hour [7:0] $end
$var reg 8 o display_min [7:0] $end
$var reg 8 p display_sec [7:0] $end
$var reg 1 U is_pm $end
$upscope $end
$scope module date_module $end
$var wire 1 4 clk $end
$var wire 8 q current_24_hour [7:0] $end
$var wire 8 r current_24_min [7:0] $end
$var wire 8 s current_24_sec [7:0] $end
$var wire 8 t input_day [7:0] $end
$var wire 8 u input_month [7:0] $end
$var wire 16 v input_year [15:0] $end
$var wire 1 ? reset $end
$var wire 1 A set_date $end
$var reg 8 w current_day [7:0] $end
$var reg 8 x current_month [7:0] $end
$var reg 16 y current_year [15:0] $end
$var reg 8 z days_in_current_month [7:0] $end
$upscope $end
$scope module timer_module $end
$var wire 1 4 clk $end
$var wire 8 { input_min [7:0] $end
$var wire 8 | input_sec [7:0] $end
$var wire 1 ? reset $end
$var wire 1 C set_timer $end
$var wire 1 D start_timer $end
$var wire 1 E stop_timer $end
$var reg 8 } max_min [7:0] $end
$var reg 1 % timer_buzzer $end
$var reg 8 ~ timer_min [7:0] $end
$var reg 1 # timer_running $end
$var reg 8 !" timer_sec [7:0] $end
$upscope $end
$upscope $end
$upscope $end
$enddefinitions $end
$comment Show the parameter values. $end
$dumpall
$end
#0
$dumpvars
b0 !"
b0 ~
b1010 }
b0 |
b0 {
bx z
b11111100100 y
b1 x
b1 w
b11111100100 v
b1 u
b1 t
b0 s
b0 r
b0 q
b0 p
b0 o
b0 n
b0 m
b0 l
b0 k
b0 j
b0 i
b0 h
bx g
bx f
bx e
b0 d
b0 c
b0 b
b0 a
b0 `
b0 _
b0 ^
b0 ]
b0 \
b1 [
b1 Z
b11111100100 Y
b0 X
b0 W
b0 V
0U
b0 T
b0 S
b0 R
b0 Q
b11111100100 P
b0 O
b1 N
b0 M
b0 L
b1 K
b0 J
b0 I
b0 H
b0 G
b0 F
0E
0D
0C
0B
0A
0@
1?
b11111100100 >
b0 =
b1 <
b0 ;
b0 :
b1 9
08
b0 7
b0 6
b0 5
04
b10000000100000 3
b0 2
b0 1
b0 0
x/
b0 .
b0 -
b0 ,
b1 +
b1 *
b11111100100 )
b0 (
b0 '
b0 &
0%
b0 $
0#
b0 "
z!
$end
#500
0/
14
#1000
04
#1500
14
#2000
04
#2500
14
#3000
04
#3500
14
#4000
04
#4500
14
#5000
04
#5500
14
#6000
04
#6500
14
#7000
04
#7500
14
#8000
04
#8500
14
#9000
04
#9500
14
#10000
04
#10500
14
#11000
04
#11500
14
#12000
04
#12500
14
#13000
04
#13500
14
#14000
04
#14500
14
#15000
04
#15500
14
#16000
04
#16500
14
#17000
04
#17500
14
#18000
04
#18500
14
#19000
04
#19500
14
#20000
04
0?
#20500
b1 7
b1 &
b1 V
b1 p
b1 ,
b1 \
b1 b
b1 m
b1 s
14
#21000
04
#21500
b10 7
b10 &
b10 V
b10 p
b10 ,
b10 \
b10 b
b10 m
b10 s
14
#22000
04
#22500
b11 7
b11 &
b11 V
b11 p
b11 ,
b11 \
b11 b
b11 m
b11 s
14
#23000
04
#23500
b100 7
b100 &
b100 V
b100 p
b100 ,
b100 \
b100 b
b100 m
b100 s
14
#24000
04
#24500
b101 7
b101 &
b101 V
b101 p
b101 ,
b101 \
b101 b
b101 m
b101 s
14
#25000
04
#25500
b110 7
b110 &
b110 V
b110 p
b110 ,
b110 \
b110 b
b110 m
b110 s
14
#26000
04
#26500
b111 7
b111 &
b111 V
b111 p
b111 ,
b111 \
b111 b
b111 m
b111 s
14
#27000
04
#27500
b1000 7
b1000 &
b1000 V
b1000 p
b1000 ,
b1000 \
b1000 b
b1000 m
b1000 s
14
#28000
04
#28500
b1001 7
b1001 &
b1001 V
b1001 p
b1001 ,
b1001 \
b1001 b
b1001 m
b1001 s
14
#29000
04
#29500
b1010 7
b1010 &
b1010 V
b1010 p
b1010 ,
b1010 \
b1010 b
b1010 m
b1010 s
14
#30000
04
b10111 :
b10111 L
b10111 h
b111011 ;
b111011 M
b111011 i
b110010 =
b110010 O
b110010 j
1B
#30500
b10111 5
b111011 6
b110010 7
b10111 (
b10111 X
b10111 n
b111011 '
b111011 W
b111011 o
b110010 &
b110010 V
b110010 p
b10111 .
b10111 ^
b10111 d
b10111 k
b10111 q
b111011 -
b111011 ]
b111011 c
b111011 l
b111011 r
b110010 ,
b110010 \
b110010 b
b110010 m
b110010 s
14
#31000
04
#31500
14
#32000
04
#32500
14
#33000
04
#33500
14
#34000
04
#34500
14
#35000
04
#35500
14
#36000
04
#36500
14
#37000
04
#37500
14
#38000
04
#38500
14
#39000
04
#39500
14
#40000
04
0B
#40500
b110011 7
b110011 &
b110011 V
b110011 p
b110011 ,
b110011 \
b110011 b
b110011 m
b110011 s
14
#41000
04
#41500
b110100 7
b110100 &
b110100 V
b110100 p
b110100 ,
b110100 \
b110100 b
b110100 m
b110100 s
14
#42000
04
#42500
b110101 7
b110101 &
b110101 V
b110101 p
b110101 ,
b110101 \
b110101 b
b110101 m
b110101 s
14
#43000
04
#43500
b110110 7
b110110 &
b110110 V
b110110 p
b110110 ,
b110110 \
b110110 b
b110110 m
b110110 s
14
#44000
04
#44500
b110111 7
b110111 &
b110111 V
b110111 p
b110111 ,
b110111 \
b110111 b
b110111 m
b110111 s
14
#45000
04
#45500
b111000 7
b111000 &
b111000 V
b111000 p
b111000 ,
b111000 \
b111000 b
b111000 m
b111000 s
14
#46000
04
#46500
b111001 7
b111001 &
b111001 V
b111001 p
b111001 ,
b111001 \
b111001 b
b111001 m
b111001 s
14
#47000
04
#47500
b111010 7
b111010 &
b111010 V
b111010 p
b111010 ,
b111010 \
b111010 b
b111010 m
b111010 s
14
#48000
04
#48500
b111011 7
b111011 &
b111011 V
b111011 p
b111011 ,
b111011 \
b111011 b
b111011 m
b111011 s
14
#49000
04
#49500
b0 5
b0 6
b0 7
b0 (
b0 X
b0 n
b0 '
b0 W
b0 o
b0 &
b0 V
b0 p
b0 .
b0 ^
b0 d
b0 k
b0 q
b0 -
b0 ]
b0 c
b0 l
b0 r
b0 ,
b0 \
b0 b
b0 m
b0 s
b10 +
b10 [
b10 w
b11111 z
14
#50000
04
b11111101001 >
b11111101001 P
b11111101001 v
b1100 <
b1100 N
b1100 u
b11111 9
b11111 K
b11111 t
1A
#50500
b1 7
b1 &
b1 V
b1 p
b11111101001 )
b11111101001 Y
b11111101001 y
b1100 *
b1100 Z
b1100 x
b11111 +
b11111 [
b11111 w
b1 ,
b1 \
b1 b
b1 m
b1 s
14
#51000
04
#51500
b10 7
b10 &
b10 V
b10 p
b10 ,
b10 \
b10 b
b10 m
b10 s
14
#52000
04
#52500
b11 7
b11 &
b11 V
b11 p
b11 ,
b11 \
b11 b
b11 m
b11 s
14
#53000
04
#53500
b100 7
b100 &
b100 V
b100 p
b100 ,
b100 \
b100 b
b100 m
b100 s
14
#54000
04
#54500
b101 7
b101 &
b101 V
b101 p
b101 ,
b101 \
b101 b
b101 m
b101 s
14
#55000
04
#55500
b110 7
b110 &
b110 V
b110 p
b110 ,
b110 \
b110 b
b110 m
b110 s
14
#56000
04
#56500
b111 7
b111 &
b111 V
b111 p
b111 ,
b111 \
b111 b
b111 m
b111 s
14
#57000
04
#57500
b1000 7
b1000 &
b1000 V
b1000 p
b1000 ,
b1000 \
b1000 b
b1000 m
b1000 s
14
#58000
04
#58500
b1001 7
b1001 &
b1001 V
b1001 p
b1001 ,
b1001 \
b1001 b
b1001 m
b1001 s
14
#59000
04
#59500
b1010 7
b1010 &
b1010 V
b1010 p
b1010 ,
b1010 \
b1010 b
b1010 m
b1010 s
14
#60000
04
b1 1
b1 I
b1 `
1@
0A
#60500
b1011 7
b1011 &
b1011 V
b1011 p
0/
b0 e
b0 f
b1010 g
b1011 ,
b1011 \
b1011 b
b1011 m
b1011 s
14
#61000
04
#61500
b1100 7
b1100 &
b1100 V
b1100 p
0/
b1011 g
b1100 ,
b1100 \
b1100 b
b1100 m
b1100 s
14
#62000
04
#62500
b1101 7
b1101 &
b1101 V
b1101 p
0/
b1100 g
b1101 ,
b1101 \
b1101 b
b1101 m
b1101 s
14
#63000
04
#63500
b1110 7
b1110 &
b1110 V
b1110 p
0/
b1101 g
b1110 ,
b1110 \
b1110 b
b1110 m
b1110 s
14
#64000
04
#64500
b1111 7
b1111 &
b1111 V
b1111 p
0/
b1110 g
b1111 ,
b1111 \
b1111 b
b1111 m
b1111 s
14
#65000
04
#65500
b10000 7
b10000 &
b10000 V
b10000 p
0/
b1111 g
b10000 ,
b10000 \
b10000 b
b10000 m
b10000 s
14
#66000
04
#66500
b10001 7
b10001 &
b10001 V
b10001 p
0/
b10000 g
b10001 ,
b10001 \
b10001 b
b10001 m
b10001 s
14
#67000
04
#67500
b10010 7
b10010 &
b10010 V
b10010 p
0/
b10001 g
b10010 ,
b10010 \
b10010 b
b10010 m
b10010 s
14
#68000
04
#68500
b10011 7
b10011 &
b10011 V
b10011 p
0/
b10010 g
b10011 ,
b10011 \
b10011 b
b10011 m
b10011 s
14
#69000
04
#69500
b10100 7
b10100 &
b10100 V
b10100 p
0/
b10011 g
b10100 ,
b10100 \
b10100 b
b10100 m
b10100 s
14
#70000
04
0@
#70500
b10101 7
b10101 &
b10101 V
b10101 p
b10101 ,
b10101 \
b10101 b
b10101 m
b10101 s
14
#71000
04
#71500
b10110 7
b10110 &
b10110 V
b10110 p
b10110 ,
b10110 \
b10110 b
b10110 m
b10110 s
14
#72000
04
#72500
b10111 7
b10111 &
b10111 V
b10111 p
b10111 ,
b10111 \
b10111 b
b10111 m
b10111 s
14
#73000
04
#73500
b11000 7
b11000 &
b11000 V
b11000 p
b11000 ,
b11000 \
b11000 b
b11000 m
b11000 s
14
#74000
04
#74500
b11001 7
b11001 &
b11001 V
b11001 p
b11001 ,
b11001 \
b11001 b
b11001 m
b11001 s
14
#75000
04
#75500
b11010 7
b11010 &
b11010 V
b11010 p
b11010 ,
b11010 \
b11010 b
b11010 m
b11010 s
14
#76000
04
#76500
b11011 7
b11011 &
b11011 V
b11011 p
b11011 ,
b11011 \
b11011 b
b11011 m
b11011 s
14
#77000
04
#77500
b11100 7
b11100 &
b11100 V
b11100 p
b11100 ,
b11100 \
b11100 b
b11100 m
b11100 s
14
#78000
04
#78500
b11101 7
b11101 &
b11101 V
b11101 p
b11101 ,
b11101 \
b11101 b
b11101 m
b11101 s
14
#79000
04
#79500
b11110 7
b11110 &
b11110 V
b11110 p
b11110 ,
b11110 \
b11110 b
b11110 m
b11110 s
14
#80000
04
b1010 G
b1010 R
b1010 |
1C
#80500
b11111 7
b11111 &
b11111 V
b11111 p
b1010 "
b1010 S
b1010 !"
b11111 ,
b11111 \
b11111 b
b11111 m
b11111 s
14
#81000
04
#81500
b100000 7
b100000 &
b100000 V
b100000 p
b100000 ,
b100000 \
b100000 b
b100000 m
b100000 s
14
#82000
04
#82500
b100001 7
b100001 &
b100001 V
b100001 p
b100001 ,
b100001 \
b100001 b
b100001 m
b100001 s
14
#83000
04
#83500
b100010 7
b100010 &
b100010 V
b100010 p
b100010 ,
b100010 \
b100010 b
b100010 m
b100010 s
14
#84000
04
#84500
b100011 7
b100011 &
b100011 V
b100011 p
b100011 ,
b100011 \
b100011 b
b100011 m
b100011 s
14
#85000
04
#85500
b100100 7
b100100 &
b100100 V
b100100 p
b100100 ,
b100100 \
b100100 b
b100100 m
b100100 s
14
#86000
04
#86500
b100101 7
b100101 &
b100101 V
b100101 p
b100101 ,
b100101 \
b100101 b
b100101 m
b100101 s
14
#87000
04
#87500
b100110 7
b100110 &
b100110 V
b100110 p
b100110 ,
b100110 \
b100110 b
b100110 m
b100110 s
14
#88000
04
#88500
b100111 7
b100111 &
b100111 V
b100111 p
b100111 ,
b100111 \
b100111 b
b100111 m
b100111 s
14
#89000
04
#89500
b101000 7
b101000 &
b101000 V
b101000 p
b101000 ,
b101000 \
b101000 b
b101000 m
b101000 s
14
#90000
04
0C
#90500
b101001 7
b101001 &
b101001 V
b101001 p
b101001 ,
b101001 \
b101001 b
b101001 m
b101001 s
14
