main.v
module clock_handler (
    input clk,
    input reset,
    input hour_format, // 1 for 12 hour, 0 for 24 hour format
    input set_time,
    input [7:0] input_sec,
    input [7:0] input_min,
    input [7:0] input_hour,

    output reg [7:0] current_24_sec,
    output reg [7:0] current_24_min,
    output reg [7:0] current_24_hour,
    output reg [7:0] display_sec,
    output reg [7:0] display_min,
    output reg [7:0] display_hour,
    output reg is_pm
);

// synchronous time set and update
always @(posedge clk or posedge reset) begin
    if (reset) begin
        current_24_sec  <= 0;
        current_24_min  <= 0;
        current_24_hour <= 0;
    end else if (set_time == 1'd1) begin
        current_24_sec  <= input_sec;
        current_24_min  <= input_min;
        current_24_hour <= input_hour;
    end else begin
        if (current_24_sec == 8'd59) begin
            current_24_sec <= 8'd0;
            if (current_24_min == 8'd59) begin
                current_24_min <= 8'd0;
                if (current_24_hour == 8'd23) begin
                    current_24_hour <= 8'd0;
                end else begin
                    current_24_hour <= current_24_hour + 1;
                end
            end else begin
                current_24_min <= current_24_min + 1;
            end
        end else begin
            current_24_sec <= current_24_sec + 1;
        end
    end
end

// Display time in 12-hour or 24-hour format
always @(*) begin
    display_sec <= current_24_sec;
    display_min <= current_24_min;

    if (hour_format == 1'b1) begin  // 12-hour format
        if (current_24_hour == 0) begin
            display_hour <= 8'd12;  // 12 AM (midnight)
        end else if (current_24_hour == 12) begin
            display_hour <= 8'd12;  // 12 PM (noon)
        end else if (current_24_hour > 12) begin
            display_hour <= current_24_hour - 12;  // PM hours
        end else begin
            display_hour <= current_24_hour;  // AM hours
        end
    end else begin  // 24-hour format
        display_hour <= current_24_hour;
    end

    if (hour_format == 1'b1) begin  // 12-hour format
        is_pm <= (current_24_hour >= 12) ? 1'b1 : 1'b0;
    end else begin
        is_pm <= 1'b0;  // Don't care in 24-hour mode
    end
end

endmodule

module date_handler (
    input clk,
    input reset,
    input set_date,
    input [7:0] input_day,
    input [7:0] input_month,
    input [15:0] input_year,

    // Clock time inputs to detect day changes
    input [7:0] current_24_hour,
    input [7:0] current_24_min,
    input [7:0] current_24_sec,

    // Date outputs
    output reg [ 7:0] current_day,
    output reg [ 7:0] current_month,
    output reg [15:0] current_year
);

// Internal signals
reg [7:0] days_in_current_month;

// Date handling logic
always @(posedge clk or posedge reset) begin
    if (reset) begin
        // Reset to default date
        current_day   <= 8'd1;
        current_month <= 8'd1;
        current_year  <= 16'd2020;

    end else if (set_date) begin
        // Set date manually when set_date is active
        current_day   <= input_day;
        current_month <= input_month;
        current_year  <= input_year;

    end else if (current_24_hour == 8'd23 && current_24_min == 8'd59 && current_24_sec == 8'd59) begin
        // Day changes at midnight (23:59:59)

        // First determine days in current month without using a function
        case (current_month)
            8'd1, 8'd3, 8'd5, 8'd7, 8'd8, 8'd10, 8'd12:
                days_in_current_month = 8'd31;  // Jan, Mar, May, Jul, Aug, Oct, Dec

            8'd4, 8'd6, 8'd9, 8'd11: days_in_current_month = 8'd30;  // Apr, Jun, Sep, Nov

            8'd2: begin  // February
                // Check leap year
                if (((current_year % 4 == 0) && (current_year % 100 != 0)) || (current_year % 400 == 0))
                    days_in_current_month = 8'd29;  // Leap year
                else days_in_current_month = 8'd28;  // Non-leap year
            end

            default: days_in_current_month = 8'd30;  // Default case
        endcase

        // Update date
        if (current_day == days_in_current_month) begin
            current_day <= 8'd1;  // Reset day to 1

            if (current_month == 8'd12) begin
                current_month <= 8'd1;  // Reset month to January
                current_year  <= current_year + 16'd1;  // Increment year
            end else begin
                current_month <= current_month + 8'd1;  // Increment month
            end
        end else begin
            current_day <= current_day + 8'd1;  // Increment day
        end
    end
end

endmodule

module alarm_handler (
    input clk,
    input set_alarm,

    input [7:0] input_sec,
    input [7:0] input_min,
    input [7:0] input_hour,

    input [7:0] alarm_time_sec,
    input [7:0] alarm_time_min,
    input [7:0] alarm_time_hour,

    input snooze_alarm,
    input stop_alarm,

    output reg alarm_buzzer
);
    reg [7:0] input_sec_internal;
    reg [7:0] input_min_internal;
    reg [7:0] input_hour_internal;
    reg [9:0] counter;
    reg is_buzzing;
    reg is_snoozed;

always @(posedge clk) begin
    // Stop alarm functionality
    if(stop_alarm) begin
        is_buzzing <= 0;
        alarm_buzzer <= 0;
    end
    // Snooze alarm functionality
    else if(snooze_alarm) begin
        is_snoozed <= 1;
        is_buzzing <= 0;
        alarm_buzzer <= 0;
        counter <= 0;
    end
    // Set alarm functionality
    else if(set_alarm) begin
        input_sec_internal <= input_sec;
        input_min_internal <= input_min;
        input_hour_internal <= input_hour;
        is_buzzing <= 0;
        is_snoozed <= 0;
        alarm_buzzer <= 0;
        counter <= 0;
    end
    // Snooze timer functionality
    else if(is_snoozed) begin
        counter <= counter + 1;
        if(counter >= 300) begin  // After snooze period (300 clock cycles)
            is_snoozed <= 0;
            counter <= 0;
        end
    end
    // Alarm matching current time
    else if ((input_sec_internal == alarm_time_sec && 
              input_min_internal == alarm_time_min && 
              input_hour_internal == alarm_time_hour) || is_buzzing) begin
        if(!is_buzzing) begin
            is_buzzing <= 1;
        end
        alarm_buzzer <= 1;
    end
    // Default state - alarm not active
    else begin
        alarm_buzzer <= 0;
    end
end

endmodule

module timer_handler (
    input clk,
    input reset,
    input start_timer,
    input stop_timer,
    input set_timer,
    input [7:0] input_min,
    input [7:0] input_sec,

    output reg [7:0] timer_min,
    output reg [7:0] timer_sec,
    output reg timer_running,
    output reg timer_buzzer
);

reg [7:0] max_min = 8'd10;

always @(posedge clk or posedge reset) begin
    if (reset) begin
        timer_min <= 8'd0;
        timer_sec <= 8'd0;
        timer_running <= 1'b0;
        timer_buzzer <= 1'b0;
    end else if (set_timer) begin
        if (input_min > max_min) begin
            // Limit to maximum 10 minutes
            timer_min <= max_min;
            timer_sec <= input_sec;
        end else begin
            timer_min <= input_min;
            timer_sec <= input_sec;
        end
        timer_running <= 1'b0;
        timer_buzzer <= 1'b0;
    end else if (start_timer) begin
        timer_running <= 1'b1;
        timer_buzzer <= 1'b0;
    end else if (stop_timer) begin
        // Stop the timer
        timer_running <= 1'b0;
    end

    if (timer_running) begin
        // Timer is running, decrement
        if (timer_sec == 8'd0) begin
            if (timer_min == 8'd0) begin
                // Timer has reached zero
                timer_running <= 1'b0;
                timer_buzzer <= 1'b1;
            end else begin
                // Decrement minute, reset seconds to 59
                timer_min <= timer_min - 8'd1;
                timer_sec <= 8'd59;
            end
        end else begin
            // Decrement seconds
            timer_sec <= timer_sec - 8'd1;
        end
    end
end

endmodule

module main_driver (
    input        clk,
    input        reset,
    input        hour_format,
    input        set_time,
    input        set_date,
    input        set_alarm,
    input        snooze_alarm,
    input        stop_alarm,
    input        set_timer,
    input        start_timer,
    input        stop_timer,

    input  [7:0] input_sec,
    input  [7:0] input_min,
    input  [7:0] input_hour,
    input  [7:0] input_day,
    input  [7:0] input_month,
    input [15:0] input_year,
    input  [7:0] timer_input_min,
    input  [7:0] timer_input_sec,
    input  [7:0] alarm_time_sec,
    input  [7:0] alarm_time_min,
    input  [7:0] alarm_time_hour,

    output [7:0] current_24_sec,
    output [7:0] current_24_min,
    output [7:0] current_24_hour,
    output [7:0] display_sec,
    output [7:0] display_min,
    output [7:0] display_hour,
    output [7:0] current_day,
    output [7:0] current_month,
    output [15:0] current_year,
    output [7:0] timer_min,
    output [7:0] timer_sec,
    output       timer_running,
    output       timer_buzzer,
    output       alarm_buzzer
);
    // Instantiate the clock_handler module
    clock_handler clock_module (
        .clk(clk),
        .reset(reset),
        .hour_format(hour_format),
        .set_time(set_time),
        .input_sec(input_sec),
        .input_min(input_min),
        .input_hour(input_hour),
        .current_24_sec(current_24_sec),
        .current_24_min(current_24_min),
        .current_24_hour(current_24_hour),
        .display_sec(display_sec),
        .display_min(display_min),
        .display_hour(display_hour),
        .is_pm(is_pm)
    );

    // Instantiate the date_handler module
    date_handler date_module (
        .clk(clk),
        .reset(reset),
        .set_date(set_date),
        .input_day(input_day),
        .input_month(input_month),
        .input_year(input_year),
        .current_24_hour(current_24_hour),
        .current_24_min(current_24_min),
        .current_24_sec(current_24_sec),
        .current_day(current_day),
        .current_month(current_month),
        .current_year(current_year)
    );

    // Instantiate the timer_handler module
    timer_handler timer_module (
        .clk(clk),
        .reset(reset),
        .set_timer(set_timer),
        .start_timer(start_timer),
        .stop_timer(stop_timer),
        .input_min(timer_input_min),
        .input_sec(timer_input_sec),
        .timer_min(timer_min),
        .timer_sec(timer_sec),
        .timer_running(timer_running),
        .timer_buzzer(timer_buzzer)
    );

    // Instantiate the alarm_handler module
    alarm_handler alarm_module (
        .clk(clk),
        .set_alarm(set_alarm),
        .snooze_alarm(snooze_alarm),
        .stop_alarm(stop_alarm),
        .input_sec(current_24_sec),
        .input_min(current_24_min),
        .input_hour(current_24_hour),
        .alarm_time_sec(alarm_time_sec),
        .alarm_time_min(alarm_time_min),
        .alarm_time_hour(alarm_time_hour),
        .alarm_buzzer(alarm_buzzer)
    );

endmodule

main_tb.v
`timescale 1s/1ms

module digital_clock_tb;
    // Clock and reset signals
    reg clk;
    reg reset;

    // Clock time control signals
    reg set_time;
    reg [7:0] input_sec;
    reg [7:0] input_min;
    reg [7:0] input_hour;
    reg hour_format;

    // Date control signals
    reg set_date;
    reg [7:0] input_day;
    reg [7:0] input_month;
    reg [15:0] input_year;

    // Timer control signals
    reg set_timer;
    reg start_timer;
    reg stop_timer;
    reg [7:0] timer_input_min;
    reg [7:0] timer_input_sec;

    // Alarm control signals
    reg set_alarm;
    reg snooze_alarm;
    reg stop_alarm;
    reg [7:0] alarm_time_sec;
    reg [7:0] alarm_time_min;
    reg [7:0] alarm_time_hour;

    // Clock time outputs
    wire [7:0] current_24_sec;
    wire [7:0] current_24_min;
    wire [7:0] current_24_hour;
    wire [7:0] display_sec;
    wire [7:0] display_min;
    wire [7:0] display_hour;
    wire is_pm;

    // Date outputs
    wire [7:0] current_day;
    wire [7:0] current_month;
    wire [15:0] current_year;

    // Timer outputs
    wire [7:0] timer_min;
    wire [7:0] timer_sec;
    wire timer_running;
    wire timer_buzzer;

    // Alarm outputs
    wire alarm_buzzer;

    // Display variables for monitoring
    reg [7:0] display_seconds;
    reg [7:0] display_minutes;
    reg [7:0] display_hours;

    // Indicator to display am or pm on the screen
    reg [15:0] am_pm_indicator;

    // Instantiating the main driver for the clock
    main_driver dut (
        .clk(clk),
        .reset(reset),
        .hour_format(hour_format),
        .set_time(set_time),
        .set_date(set_date),
        .set_alarm(set_alarm),
        .snooze_alarm(snooze_alarm),
        .stop_alarm(stop_alarm),
        .set_timer(set_timer),
        .start_timer(start_timer),
        .stop_timer(stop_timer),
        .input_sec(input_sec),
        .input_min(input_min),
        .input_hour(input_hour),
        .input_day(input_day),
        .input_month(input_month),
        .input_year(input_year),
        .timer_input_min(timer_input_min),
        .timer_input_sec(timer_input_sec),
        .alarm_time_sec(alarm_time_sec),
        .alarm_time_min(alarm_time_min),
        .alarm_time_hour(alarm_time_hour),
        .current_24_sec(current_24_sec),
        .current_24_min(current_24_min),
        .current_24_hour(current_24_hour),
        .display_sec(display_sec),
        .display_min(display_min),
        .display_hour(display_hour),
        .current_day(current_day),
        .current_month(current_month),
        .current_year(current_year),
        .timer_min(timer_min),
        .timer_sec(timer_sec),
        .timer_running(timer_running),
        .timer_buzzer(timer_buzzer),
        .alarm_buzzer(alarm_buzzer)
    );

    // Clock generation
    initial begin
        clk = 0;
        forever #0.5 clk = ~clk;
    end

    // Display logic - show timer when running, otherwise show clock
    always @(*) begin
        if (timer_running) begin
            display_seconds = timer_sec;
            display_minutes = timer_min;
            display_hours = 8'd0; // Timer doesn't use hours
        end else begin
            display_seconds = display_sec;
            display_minutes = display_min;
            display_hours = display_hour;
        end

        if (hour_format) begin
            if (is_pm)
                am_pm_indicator = {"P", "M"};  // 'P' = 8'h50, 'M' = 8'h4D
            else
                am_pm_indicator = {"A", "M"};  // 'A' = 8'h41, 'M' = 8'h4D
        end else begin
            am_pm_indicator = "  ";  // Two spaces if 24-hour
        end
    end

    // Test sequence
    initial begin
        // Initialize all inputs
        reset = 1;
        set_time = 0;
        input_sec = 0;
        input_min = 0;
        input_hour = 0;
        hour_format = 0;
        set_date = 0;
        input_day = 1;
        input_month = 1;
        input_year = 2020;
        set_alarm = 0;
        set_timer = 0;
        start_timer = 0;
        stop_timer = 0;
        timer_input_min = 0;
        timer_input_sec = 0;
        alarm_time_sec = 0;
        alarm_time_min = 0;
        alarm_time_hour = 0;
        snooze_alarm = 0;
        stop_alarm = 0;

        // Apply reset for 20ns
        #20 reset = 0;

        // Test 1: Set the time to 23:59:50
        #10;
        set_time = 1;
        input_sec = 50;
        input_min = 59;
        input_hour = 23;
        #10;
        set_time = 0;

        // Test 2: Set the date to December 31, 2025
        #10;
        set_date = 1;
        input_day = 31;
        input_month = 12;
        input_year = 2025;
        #10; set_date = 0;

        // Test 3: Set an alarm for 00:01:00
        set_alarm = 1;
        alarm_time_sec = 0;
        alarm_time_min = 1;
        alarm_time_hour = 0;
        #10;
        set_alarm = 0;

        // Test 4: Set and start a 10-second timer
        #10;
        set_timer = 1;
        timer_input_min = 0;
        timer_input_sec = 10;
        #10;
        set_timer = 0;
        #10;
        start_timer = 1;
        #10;
        start_timer = 0;

        // Wait for the timer to run for a bit
        #200;

        // Test 5: Stop the timer
        stop_timer = 1;
        #10;
        stop_timer = 0;

        // Test 6: Wait for the clock to roll over to the next day
        // We'll speed up time by setting it closer to midnight
        #10;
        set_time = 1;
        input_sec = 58;
        input_min = 59;
        input_hour = 23;
        #10;
        set_time = 0;

        // Wait for date to change (about 30 seconds in simulation time)
        #300;

        // Test 7: Switch to 12-hour format
        hour_format = 1;
        #100;

        // Test 8: Set a new timer and let it complete
        #10;
        set_timer = 1;
        timer_input_min = 0;
        timer_input_sec = 5; // 5-second timer
        #10;
        set_timer = 0;
        #10;
        start_timer = 1;
        #10;
        start_timer = 0;

        // Wait for the timer to finish
        #600;

        // End simulation
        #100 $finish;
    end

   // Monitor outputs
   initial begin
       $monitor("DISPLAY: %02d:%02d:%02d %c%c | DATE: %02d/%02d/%4d\nTime: %3ds | Clock: %02d:%02d:%02d\nTimer: %02d:%02d (Running: %b, Done: %b)\nAlarm Buzzer: %0d | Alarm: sec=%d, min=%d, hour=%d\nControls: set_time=%b | set_date=%b | set_timer=%b | start=%b | stop=%b | hour_format=%b | reset=%b\nInputs: sec=%d, min=%d, hour=%d, day=%d, month=%d, year=%d\nTimer Inputs: min=%d, sec=%d\nAlarm Inputs: snooze=%d, stop=%d\n",
           display_hours, display_minutes, display_seconds,
           am_pm_indicator[15:8], am_pm_indicator[7:0],
           current_day, current_month, current_year,
           $time,
           current_24_hour, current_24_min, current_24_sec,
           timer_min, timer_sec, timer_running, timer_buzzer,
           alarm_buzzer, alarm_time_sec, alarm_time_min, alarm_time_hour,
           set_time, set_date, set_timer, start_timer, stop_timer, hour_format, reset,
           input_sec, input_min, input_hour, input_day, input_month, input_year,
           timer_input_min, timer_input_sec,
           snooze_alarm, stop_alarm);
   end

   initial begin
       $dumpfile("wave.vcd");
       $dumpvars(0, digital_clock_tb);
   end

endmodule

wave.vcd
$date
	Wed May  7 16:41:57 2025
$end
$version
	Icarus Verilog
$end
$timescale
	1ms
$end
$scope module digital_clock_tb $end
$var wire 1 ! is_pm $end
$var wire 8 " timer_sec [7:0] $end
$var wire 1 # timer_running $end
$var wire 8 $ timer_min [7:0] $end
$var wire 1 % timer_buzzer $end
$var wire 8 & display_sec [7:0] $end
$var wire 8 ' display_min [7:0] $end
$var wire 8 ( display_hour [7:0] $end
$var wire 16 ) current_year [15:0] $end
$var wire 8 * current_month [7:0] $end
$var wire 8 + current_day [7:0] $end
$var wire 8 , current_24_sec [7:0] $end
$var wire 8 - current_24_min [7:0] $end
$var wire 8 . current_24_hour [7:0] $end
$var wire 1 / alarm_buzzer $end
$var reg 8 0 alarm_time_hour [7:0] $end
$var reg 8 1 alarm_time_min [7:0] $end
$var reg 8 2 alarm_time_sec [7:0] $end
$var reg 16 3 am_pm_indicator [15:0] $end
$var reg 1 4 clk $end
$var reg 8 5 display_hours [7:0] $end
$var reg 8 6 display_minutes [7:0] $end
$var reg 8 7 display_seconds [7:0] $end
$var reg 1 8 hour_format $end
$var reg 8 9 input_day [7:0] $end
$var reg 8 : input_hour [7:0] $end
$var reg 8 ; input_min [7:0] $end
$var reg 8 < input_month [7:0] $end
$var reg 8 = input_sec [7:0] $end
$var reg 16 > input_year [15:0] $end
$var reg 1 ? reset $end
$var reg 1 @ set_alarm $end
$var reg 1 A set_date $end
$var reg 1 B set_time $end
$var reg 1 C set_timer $end
$var reg 1 D snooze_alarm $end
$var reg 1 E start_timer $end
$var reg 1 F stop_alarm $end
$var reg 1 G stop_timer $end
$var reg 8 H timer_input_min [7:0] $end
$var reg 8 I timer_input_sec [7:0] $end
$scope module dut $end
$var wire 8 J alarm_time_hour [7:0] $end
$var wire 8 K alarm_time_min [7:0] $end
$var wire 8 L alarm_time_sec [7:0] $end
$var wire 1 4 clk $end
$var wire 1 8 hour_format $end
$var wire 8 M input_day [7:0] $end
$var wire 8 N input_hour [7:0] $end
$var wire 8 O input_min [7:0] $end
$var wire 8 P input_month [7:0] $end
$var wire 8 Q input_sec [7:0] $end
$var wire 16 R input_year [15:0] $end
$var wire 1 ? reset $end
$var wire 1 @ set_alarm $end
$var wire 1 A set_date $end
$var wire 1 B set_time $end
$var wire 1 C set_timer $end
$var wire 1 D snooze_alarm $end
$var wire 1 E start_timer $end
$var wire 1 F stop_alarm $end
$var wire 1 G stop_timer $end
$var wire 8 S timer_input_min [7:0] $end
$var wire 8 T timer_input_sec [7:0] $end
$var wire 8 U timer_sec [7:0] $end
$var wire 1 # timer_running $end
$var wire 8 V timer_min [7:0] $end
$var wire 1 % timer_buzzer $end
$var wire 1 W is_pm $end
$var wire 8 X display_sec [7:0] $end
$var wire 8 Y display_min [7:0] $end
$var wire 8 Z display_hour [7:0] $end
$var wire 16 [ current_year [15:0] $end
$var wire 8 \ current_month [7:0] $end
$var wire 8 ] current_day [7:0] $end
$var wire 8 ^ current_24_sec [7:0] $end
$var wire 8 _ current_24_min [7:0] $end
$var wire 8 ` current_24_hour [7:0] $end
$var wire 1 / alarm_buzzer $end
$scope module alarm_module $end
$var wire 8 a alarm_time_hour [7:0] $end
$var wire 8 b alarm_time_min [7:0] $end
$var wire 8 c alarm_time_sec [7:0] $end
$var wire 1 4 clk $end
$var wire 1 @ set_alarm $end
$var wire 1 D snooze_alarm $end
$var wire 1 F stop_alarm $end
$var wire 8 d input_sec [7:0] $end
$var wire 8 e input_min [7:0] $end
$var wire 8 f input_hour [7:0] $end
$var reg 1 / alarm_buzzer $end
$var reg 10 g counter [9:0] $end
$var reg 8 h input_hour_internal [7:0] $end
$var reg 8 i input_min_internal [7:0] $end
$var reg 8 j input_sec_internal [7:0] $end
$var reg 1 k is_buzzing $end
$var reg 1 l is_snoozed $end
$upscope $end
$scope module clock_module $end
$var wire 1 4 clk $end
$var wire 1 8 hour_format $end
$var wire 8 m input_hour [7:0] $end
$var wire 8 n input_min [7:0] $end
$var wire 8 o input_sec [7:0] $end
$var wire 1 ? reset $end
$var wire 1 B set_time $end
$var reg 8 p current_24_hour [7:0] $end
$var reg 8 q current_24_min [7:0] $end
$var reg 8 r current_24_sec [7:0] $end
$var reg 8 s display_hour [7:0] $end
$var reg 8 t display_min [7:0] $end
$var reg 8 u display_sec [7:0] $end
$var reg 1 W is_pm $end
$upscope $end
$scope module date_module $end
$var wire 1 4 clk $end
$var wire 8 v current_24_hour [7:0] $end
$var wire 8 w current_24_min [7:0] $end
$var wire 8 x current_24_sec [7:0] $end
$var wire 8 y input_day [7:0] $end
$var wire 8 z input_month [7:0] $end
$var wire 16 { input_year [15:0] $end
$var wire 1 ? reset $end
$var wire 1 A set_date $end
$var reg 8 | current_day [7:0] $end
$var reg 8 } current_month [7:0] $end
$var reg 16 ~ current_year [15:0] $end
$var reg 8 !" days_in_current_month [7:0] $end
$upscope $end
$scope module timer_module $end
$var wire 1 4 clk $end
$var wire 8 "" input_min [7:0] $end
$var wire 8 #" input_sec [7:0] $end
$var wire 1 ? reset $end
$var wire 1 C set_timer $end
$var wire 1 E start_timer $end
$var wire 1 G stop_timer $end
$var reg 8 $" max_min [7:0] $end
$var reg 1 % timer_buzzer $end
$var reg 8 %" timer_min [7:0] $end
$var reg 1 # timer_running $end
$var reg 8 &" timer_sec [7:0] $end
$upscope $end
$upscope $end
$upscope $end
$enddefinitions $end
$comment Show the parameter values. $end
$dumpall
$end
#0
$dumpvars
b0 &"
b0 %"
b1010 $"
b0 #"
b0 ""
bx !"
b11111100100 ~
b1 }
b1 |
b11111100100 {
b1 z
b1 y
b0 x
b0 w
b0 v
b0 u
b0 t
b0 s
b0 r
b0 q
b0 p
b0 o
b0 n
b0 m
xl
xk
bx j
bx i
bx h
bx g
b0 f
b0 e
b0 d
b0 c
b0 b
b0 a
b0 `
b0 _
b0 ^
b1 ]
b1 \
b11111100100 [
b0 Z
b0 Y
b0 X
0W
b0 V
b0 U
b0 T
b0 S
b11111100100 R
b0 Q
b1 P
b0 O
b0 N
b1 M
b0 L
b0 K
b0 J
b0 I
b0 H
0G
0F
0E
0D
0C
0B
0A
0@
1?
b11111100100 >
b0 =
b1 <
b0 ;
b0 :
b1 9
08
b0 7
b0 6
b0 5
04
b10000000100000 3
b0 2
b0 1
b0 0
x/
b0 .
b0 -
b0 ,
b1 +
b1 *
b11111100100 )
b0 (
b0 '
b0 &
0%
b0 $
0#
b0 "
z!
$end
#500
0/
14
#1000
04
#1500
14
#2000
04
#2500
14
#3000
04
#3500
14
#4000
04
#4500
14
#5000
04
#5500
14
#6000
04
#6500
14
#7000
04
#7500
14
#8000
04
#8500
14
#9000
04
#9500
14
#10000
04
#10500
14
#11000
04
#11500
14
#12000
04
#12500
14
#13000
04
#13500
14
#14000
04
#14500
14
#15000
04
#15500
14
#16000
04
#16500
14
#17000
04
#17500
14
#18000
04
#18500
14
#19000
04
#19500
14
#20000
04
0?
#20500
b1 7
b1 &
b1 X
b1 u
b1 ,
b1 ^
b1 d
b1 r
b1 x
14
#21000
04
#21500
b10 7
b10 &
b10 X
b10 u
b10 ,
b10 ^
b10 d
b10 r
b10 x
14
#22000
04
#22500
b11 7
b11 &
b11 X
b11 u
b11 ,
b11 ^
b11 d
b11 r
b11 x
14
#23000
04
#23500
b100 7
b100 &
b100 X
b100 u
b100 ,
b100 ^
b100 d
b100 r
b100 x
14
#24000
04
#24500
b101 7
b101 &
b101 X
b101 u
b101 ,
b101 ^
b101 d
b101 r
b101 x
14
#25000
04
#25500
b110 7
b110 &
b110 X
b110 u
b110 ,
b110 ^
b110 d
b110 r
b110 x
14
#26000
04
#26500
b111 7
b111 &
b111 X
b111 u
b111 ,
b111 ^
b111 d
b111 r
b111 x
14
#27000
04
#27500
b1000 7
b1000 &
b1000 X
b1000 u
b1000 ,
b1000 ^
b1000 d
b1000 r
b1000 x
14
#28000
04
#28500
b1001 7
b1001 &
b1001 X
b1001 u
b1001 ,
b1001 ^
b1001 d
b1001 r
b1001 x
14
#29000
04
#29500
b1010 7
b1010 &
b1010 X
b1010 u
b1010 ,
b1010 ^
b1010 d
b1010 r
b1010 x
14
#30000
04
b10111 :
b10111 N
b10111 m
b111011 ;
b111011 O
b111011 n
b110010 =
b110010 Q
b110010 o
1B
#30500
b10111 5
b111011 6
b110010 7
b10111 (
b10111 Z
b10111 s
b111011 '
b111011 Y
b111011 t
b110010 &
b110010 X
b110010 u
b10111 .
b10111 `
b10111 f
b10111 p
b10111 v
b111011 -
b111011 _
b111011 e
b111011 q
b111011 w
b110010 ,
b110010 ^
b110010 d
b110010 r
b110010 x
14
#31000
04
#31500
14
#32000
04
#32500
14
#33000
04
#33500
14
#34000
04
#34500
14
#35000
04
#35500
14
#36000
04
#36500
14
#37000
04
#37500
14
#38000
04
#38500
14
#39000
04
#39500
14
#40000
04
0B
#40500
b110011 7
b110011 &
b110011 X
b110011 u
b110011 ,
b110011 ^
b110011 d
b110011 r
b110011 x
14
#41000
04
#41500
b110100 7
b110100 &
b110100 X
b110100 u
b110100 ,
b110100 ^
b110100 d
b110100 r
b110100 x
14
#42000
04
#42500
b110101 7
b110101 &
b110101 X
b110101 u
b110101 ,
b110101 ^
b110101 d
b110101 r
b110101 x
14
#43000
04
#43500
b110110 7
b110110 &
b110110 X
b110110 u
b110110 ,
b110110 ^
b110110 d
b110110 r
b110110 x
14
#44000
04
#44500
b110111 7
b110111 &
b110111 X
b110111 u
b110111 ,
b110111 ^
b110111 d
b110111 r
b110111 x
14
#45000
04
#45500
b111000 7
b111000 &
b111000 X
b111000 u
b111000 ,
b111000 ^
b111000 d
b111000 r
b111000 x
14
#46000
04
#46500
b111001 7
b111001 &
b111001 X
b111001 u
b111001 ,
b111001 ^
b111001 d
b111001 r
b111001 x
14
#47000
04
#47500
b111010 7
b111010 &
b111010 X
b111010 u
b111010 ,
b111010 ^
b111010 d
b111010 r
b111010 x
14
#48000
04
#48500
b111011 7
b111011 &
b111011 X
b111011 u
b111011 ,
b111011 ^
b111011 d
b111011 r
b111011 x
14
#49000
04
#49500
b0 5
b0 6
b0 7
b0 (
b0 Z
b0 s
b0 '
b0 Y
b0 t
b0 &
b0 X
b0 u
b0 .
b0 `
b0 f
b0 p
b0 v
b0 -
b0 _
b0 e
b0 q
b0 w
b0 ,
b0 ^
b0 d
b0 r
b0 x
b10 +
b10 ]
b10 |
b11111 !"
14
#50000
04
b11111101001 >
b11111101001 R
b11111101001 {
b1100 <
b1100 P
b1100 z
b11111 9
b11111 M
b11111 y
1A
#50500
b1 7
b1 &
b1 X
b1 u
b11111101001 )
b11111101001 [
b11111101001 ~
b1100 *
b1100 \
b1100 }
b11111 +
b11111 ]
b11111 |
b1 ,
b1 ^
b1 d
b1 r
b1 x
14
#51000
04
#51500
b10 7
b10 &
b10 X
b10 u
b10 ,
b10 ^
b10 d
b10 r
b10 x
14
#52000
04
#52500
b11 7
b11 &
b11 X
b11 u
b11 ,
b11 ^
b11 d
b11 r
b11 x
14
#53000
04
#53500
b100 7
b100 &
b100 X
b100 u
b100 ,
b100 ^
b100 d
b100 r
b100 x
14
#54000
04
#54500
b101 7
b101 &
b101 X
b101 u
b101 ,
b101 ^
b101 d
b101 r
b101 x
14
#55000
04
#55500
b110 7
b110 &
b110 X
b110 u
b110 ,
b110 ^
b110 d
b110 r
b110 x
14
#56000
04
#56500
b111 7
b111 &
b111 X
b111 u
b111 ,
b111 ^
b111 d
b111 r
b111 x
14
#57000
04
#57500
b1000 7
b1000 &
b1000 X
b1000 u
b1000 ,
b1000 ^
b1000 d
b1000 r
b1000 x
14
#58000
04
#58500
b1001 7
b1001 &
b1001 X
b1001 u
b1001 ,
b1001 ^
b1001 d
b1001 r
b1001 x
14
#59000
04
#59500
b1010 7
b1010 &
b1010 X
b1010 u
b1010 ,
b1010 ^
b1010 d
b1010 r
b1010 x
14
#60000
04
b1 1
b1 K
b1 b
1@
0A
#60500
b1011 7
b1011 &
b1011 X
b1011 u
b0 g
0l
0k
b0 h
b0 i
b1010 j
b1011 ,
b1011 ^
b1011 d
b1011 r
b1011 x
14
#61000
04
#61500
b1100 7
b1100 &
b1100 X
b1100 u
b1011 j
b1100 ,
b1100 ^
b1100 d
b1100 r
b1100 x
14
#62000
04
#62500
b1101 7
b1101 &
b1101 X
b1101 u
b1100 j
b1101 ,
b1101 ^
b1101 d
b1101 r
b1101 x
14
#63000
04
#63500
b1110 7
b1110 &
b1110 X
b1110 u
b1101 j
b1110 ,
b1110 ^
b1110 d
b1110 r
b1110 x
14
#64000
04
#64500
b1111 7
b1111 &
b1111 X
b1111 u
b1110 j
b1111 ,
b1111 ^
b1111 d
b1111 r
b1111 x
14
#65000
04
#65500
b10000 7
b10000 &
b10000 X
b10000 u
b1111 j
b10000 ,
b10000 ^
b10000 d
b10000 r
b10000 x
14
#66000
04
#66500
b10001 7
b10001 &
b10001 X
b10001 u
b10000 j
b10001 ,
b10001 ^
b10001 d
b10001 r
b10001 x
14
#67000
04
#67500
b10010 7
b10010 &
b10010 X
b10010 u
b10001 j
b10010 ,
b10010 ^
b10010 d
b10010 r
b10010 x
14
#68000
04
#68500
b10011 7
b10011 &
b10011 X
b10011 u
b10010 j
b10011 ,
b10011 ^
b10011 d
b10011 r
b10011 x
14
#69000
04
#69500
b10100 7
b10100 &
b10100 X
b10100 u
b10011 j
b10100 ,
b10100 ^
b10100 d
b10100 r
b10100 x
14
#70000
04
0@
#70500
b10101 7
b10101 &
b10101 X
b10101 u
b10101 ,
b10101 ^
b10101 d
b10101 r
b10101 x
14
#71000
04
#71500
b10110 7
b10110 &
b10110 X
b10110 u
b10110 ,
b10110 ^
b10110 d
b10110 r
b10110 x
14
#72000
04
#72500
b10111 7
b10111 &
b10111 X
b10111 u
b10111 ,
b10111 ^
b10111 d
b10111 r
b10111 x
14
#73000
04
#73500
b11000 7
b11000 &
b11000 X
b11000 u
b11000 ,
b11000 ^
b11000 d
b11000 r
b11000 x
14
#74000
04
#74500
b11001 7
b11001 &
b11001 X
b11001 u
b11001 ,
b11001 ^
b11001 d
b11001 r
b11001 x
14
#75000
04
#75500
b11010 7
b11010 &
b11010 X
b11010 u
b11010 ,
b11010 ^
b11010 d
b11010 r
b11010 x
14
#76000
04
#76500
b11011 7
b11011 &
b11011 X
b11011 u
b11011 ,
b11011 ^
b11011 d
b11011 r
b11011 x
14
#77000
04
#77500
b11100 7
b11100 &
b11100 X
b11100 u
b11100 ,
b11100 ^
b11100 d
b11100 r
b11100 x
14
#78000
04
#78500
b11101 7
b11101 &
b11101 X
b11101 u
b11101 ,
b11101 ^
b11101 d
b11101 r
b11101 x
14
#79000
04
